{
  "data": {
    "AEFES.IS": {
      "close": 17.34,
      "high": 17.39,
      "low": 17.33,
      "open": 17.39
    },
    "AGHOL.IS": {
      "close": 28.7,
      "high": 28.78,
      "low": 28.7,
      "open": 28.74
    },
    "AKBNK.IS": {
      "close": 72.3,
      "high": 72.4,
      "low": 72.25,
      "open": 72.35
    },
    "AKSA.IS": {
      "close": 11.02,
      "high": 11.04,
      "low": 11.02,
      "open": 11.04
    },
    "AKSEN.IS": {
      "close": 76.25,
      "high": 76.3,
      "low": 76.1,
      "open": 76.25
    },
    "ALARK.IS": {
      "close": 90.45,
      "high": 90.65,
      "low": 90.4,
      "open": 90.55
    },
    "ALTNY.IS": {
      "close": 15.13,
      "high": 15.15,
      "low": 15.12,
      "open": 15.15
    },
    "ANSGR.IS": {
      "close": 28.3,
      "high": 28.32,
      "low": 28.24,
      "open": 28.24
    },
    "ARCLK.IS": {
      "close": 116.2,
      "high": 116.2,
      "low": 116.0,
      "open": 116.2
    },
    "ASELS.IS": {
      "close": 353.25,
      "high": 354.0,
      "low": 353.0,
      "open": 353.5
    },
    "ASTOR.IS": {
      "close": 193.9,
      "high": 194.5,
      "low": 193.6,
      "open": 194.4
    },
    "BALSU.IS": {
      "close": 14.27,
      "high": 14.27,
      "low": 14.24,
      "open": 14.26
    },
    "BIMAS.IS": {
      "close": 691.5,
      "high": 693.0,
      "low": 691.5,
      "open": 692.5
    },
    "BRSAN.IS": {
      "close": 514.5,
      "high": 515.5,
      "low": 514.0,
      "open": 515.0
    },
    "BRYAT.IS": {
      "close": 2215.0,
      "high": 2217.0,
      "low": 2214.0,
      "open": 2217.0
    },
    "BSOKE.IS": {
      "close": 33.0,
      "high": 33.04,
      "low": 32.96,
      "open": 33.0
    },
    "BTCIM.IS": {
      "close": 6.45,
      "high": 6.47,
      "low": 6.44,
      "open": 6.46
    },
    "CANTE.IS": {
      "close": 1.69,
      "high": 1.69,
      "low": 1.68,
      "open": 1.69
    },
    "CCOLA.IS": {
      "close": 70.7,
      "high": 70.9,
      "low": 70.7,
      "open": 70.9
    },
    "CIMSA.IS": {
      "close": 49.72,
      "high": 49.76,
      "low": 49.7,
      "open": 49.74
    },
    "CWENE.IS": {
      "close": 29.24,
      "high": 29.34,
      "low": 29.22,
      "open": 29.34
    },
    "DAPGM.IS": {
      "close": 14.66,
      "high": 14.7,
      "low": 14.65,
      "open": 14.68
    },
    "DOAS.IS": {
      "close": 197.1,
      "high": 197.4,
      "low": 197.0,
      "open": 197.2
    },
    "DOHOL.IS": {
      "close": 20.86,
      "high": 20.88,
      "low": 20.84,
      "open": 20.88
    },
    "DSTKF.IS": {
      "close": 1848.0,
      "high": 1852.0,
      "low": 1847.0,
      "open": 1852.0
    },
    "ECILC.IS": {
      "close": 119.7,
      "high": 120.2,
      "low": 119.7,
      "open": 119.9
    },
    "EFOR.IS": {
      "close": 10.16,
      "high": 10.16,
      "low": 10.16,
      "open": 10.16
    },
    "EGEEN.IS": {
      "close": 5832.5,
      "high": 5835.0,
      "low": 5822.5,
      "open": 5830.0
    },
    "EKGYO.IS": {
      "close": 20.38,
      "high": 20.42,
      "low": 20.34,
      "open": 20.4
    },
    "ENERY.IS": {
      "close": 8.72,
      "high": 8.76,
      "low": 8.72,
      "open": 8.74
    },
    "ENJSA.IS": {
      "close": 114.4,
      "high": 114.6,
      "low": 114.2,
      "open": 114.6
    },
    "ENKAI.IS": {
      "close": 97.35,
      "high": 97.4,
      "low": 97.25,
      "open": 97.3
    },
    "EREGL.IS": {
      "close": 28.48,
      "high": 28.54,
      "low": 28.46,
      "open": 28.54
    },
    "EUPWR.IS": {
      "close": 35.74,
      "high": 35.86,
      "low": 35.72,
      "open": 35.8
    },
    "FENER.IS": {
      "close": 2.73,
      "high": 2.73,
      "low": 2.72,
      "open": 2.73
    },
    "FROTO.IS": {
      "close": 108.1,
      "high": 108.3,
      "low": 108.0,
      "open": 108.3
    },
    "GARAN.IS": {
      "close": 134.0,
      "high": 134.3,
      "low": 133.9,
      "open": 134.2
    },
    "GENIL.IS": {
      "close": 9.5,
      "high": 9.52,
      "low": 9.5,
      "open": 9.5
    },
    "GESAN.IS": {
      "close": 45.22,
      "high": 45.26,
      "low": 45.16,
      "open": 45.26
    },
    "GLRMK.IS": {
      "close": 171.0,
      "high": 171.2,
      "low": 170.7,
      "open": 170.8
    },
    "GRSEL.IS": {
      "close": 316.0,
      "high": 316.75,
      "low": 316.0,
      "open": 316.5
    },
    "GRTHO.IS": {
      "close": 243.3,
      "high": 244.0,
      "low": 242.9,
      "open": 243.8
    },
    "GSRAY.IS": {
      "close": 1.09,
      "high": 1.09,
      "low": 1.08,
      "open": 1.08
    },
    "GUBRF.IS": {
      "close": 483.0,
      "high": 483.5,
      "low": 482.25,
      "open": 483.0
    },
    "HALKB.IS": {
      "close": 39.24,
      "high": 39.34,
      "low": 39.2,
      "open": 39.32
    },
    "HEKTS.IS": {
      "close": 2.99,
      "high": 3.0,
      "low": 2.98,
      "open": 2.99
    },
    "ISCTR.IS": {
      "close": 13.66,
      "high": 13.68,
      "low": 13.64,
      "open": 13.66
    },
    "ISMEN.IS": {
      "close": 46.1,
      "high": 46.14,
      "low": 45.98,
      "open": 46.0
    },
    "IZENR.IS": {
      "close": 10.08,
      "high": 10.09,
      "low": 10.06,
      "open": 10.07
    },
    "KCAER.IS": {
      "close": 11.85,
      "high": 11.92,
      "low": 11.85,
      "open": 11.92
    },
    "KCHOL.IS": {
      "close": 194.9,
      "high": 195.1,
      "low": 194.8,
      "open": 195.0
    },
    "KLRHO.IS": {
      "close": 123.3,
      "high": 124.8,
      "low": 122.5,
      "open": 123.9
    },
    "KONTR.IS": {
      "close": 9.3,
      "high": 9.32,
      "low": 9.3,
      "open": 9.31
    },
    "KRDMD.IS": {
      "close": 30.28,
      "high": 30.28,
      "low": 30.22,
      "open": 30.26
    },
    "KTLEV.IS": {
      "close": 63.0,
      "high": 63.05,
      "low": 61.9,
      "open": 61.95
    },
    "KUYAS.IS": {
      "close": 78.6,
      "high": 78.65,
      "low": 78.25,
      "open": 78.6
    },
    "MAGEN.IS": {
      "close": 48.86,
      "high": 48.94,
      "low": 48.8,
      "open": 48.88
    },
    "MAVI.IS": {
      "close": 43.72,
      "high": 43.74,
      "low": 43.64,
      "open": 43.72
    },
    "MGROS.IS": {
      "close": 594.5,
      "high": 595.5,
      "low": 594.5,
      "open": 595.5
    },
    "MIATK.IS": {
      "close": 40.14,
      "high": 40.18,
      "low": 39.8,
      "open": 39.84
    },
    "MPARK.IS": {
      "close": 437.25,
      "high": 438.75,
      "low": 437.25,
      "open": 437.25
    },
    "OBAMS.IS": {
      "close": 8.12,
      "high": 8.12,
      "low": 8.1,
      "open": 8.1
    },
    "ODAS.IS": {
      "close": 6.23,
      "high": 6.26,
      "low": 6.22,
      "open": 6.26
    },
    "OTKAR.IS": {
      "close": 388.5,
      "high": 388.75,
      "low": 387.75,
      "open": 388.5
    },
    "OYAKC.IS": {
      "close": 23.46,
      "high": 23.5,
      "low": 23.44,
      "open": 23.48
    },
    "PASEU.IS": {
      "close": 121.2,
      "high": 121.6,
      "low": 121.1,
      "open": 121.6
    },
    "PATEK.IS": {
      "close": 17.74,
      "high": 17.79,
      "low": 17.7,
      "open": 17.79
    },
    "PETKM.IS": {
      "close": 19.62,
      "high": 19.67,
      "low": 19.53,
      "open": 19.61
    },
    "PGSUS.IS": {
      "close": 180.9,
      "high": 181.3,
      "low": 180.8,
      "open": 181.1
    },
    "QUAGR.IS": {
      "close": 3.1,
      "high": 3.11,
      "low": 3.1,
      "open": 3.11
    },
    "RALYH.IS": {
      "close": 153.4,
      "high": 153.4,
      "low": 153.4,
      "open": 153.4
    },
    "REEDR.IS": {
      "close": 8.78,
      "high": 8.86,
      "low": 8.69,
      "open": 8.69
    },
    "SAHOL.IS": {
      "close": 93.25,
      "high": 93.4,
      "low": 93.2,
      "open": 93.35
    },
    "SASA.IS": {
      "close": 2.46,
      "high": 2.47,
      "low": 2.46,
      "open": 2.47
    },
    "SISE.IS": {
      "close": 48.68,
      "high": 48.68,
      "low": 48.68,
      "open": 48.68
    },
    "SKBNK.IS": {
      "close": 10.47,
      "high": 10.5,
      "low": 10.47,
      "open": 10.47
    },
    "SOKM.IS": {
      "close": 51.8,
      "high": 51.85,
      "low": 51.75,
      "open": 51.85
    },
    "TABGD.IS": {
      "close": 250.0,
      "high": 250.25,
      "low": 249.5,
      "open": 249.6
    },
    "TAVHL.IS": {
      "close": 297.5,
      "high": 298.0,
      "low": 297.25,
      "open": 298.0
    },
    "TCELL.IS": {
      "close": 107.9,
      "high": 108.1,
      "low": 107.7,
      "open": 108.1
    },
    "THYAO.IS": {
      "close": 293.75,
      "high": 294.0,
      "low": 293.25,
      "open": 294.0
    },
    "TKFEN.IS": {
      "close": 84.1,
      "high": 84.4,
      "low": 84.1,
      "open": 84.4
    },
    "TOASO.IS": {
      "close": 283.5,
      "high": 283.75,
      "low": 282.0,
      "open": 282.0
    },
    "TRALT.IS": {
      "close": 46.04,
      "high": 46.14,
      "low": 45.86,
      "open": 46.14
    },
    "TRENJ.IS": {
      "close": 97.7,
      "high": 97.85,
      "low": 97.45,
      "open": 97.7
    },
    "TRMET.IS": {
      "close": 133.1,
      "high": 133.3,
      "low": 132.6,
      "open": 132.7
    },
    "TSKB.IS": {
      "close": 12.34,
      "high": 12.34,
      "low": 12.31,
      "open": 12.34
    },
    "TSPOR.IS": {
      "close": 0.95,
      "high": 0.95,
      "low": 0.94,
      "open": 0.95
    },
    "TTKOM.IS": {
      "close": 60.0,
      "high": 60.05,
      "low": 59.95,
      "open": 60.05
    },
    "TTRAK.IS": {
      "close": 454.0,
      "high": 454.0,
      "low": 453.0,
      "open": 453.75
    },
    "TUKAS.IS": {
      "close": 2.33,
      "high": 2.34,
      "low": 2.33,
      "open": 2.34
    },
    "TUPRS.IS": {
      "close": 256.25,
      "high": 256.25,
      "low": 255.5,
      "open": 255.75
    },
    "TUREX.IS": {
      "close": 7.43,
      "high": 7.44,
      "low": 7.41,
      "open": 7.42
    },
    "TURSG.IS": {
      "close": 13.32,
      "high": 13.32,
      "low": 13.3,
      "open": 13.31
    },
    "ULKER.IS": {
      "close": 111.8,
      "high": 111.8,
      "low": 111.6,
      "open": 111.7
    },
    "VAKBN.IS": {
      "close": 33.06,
      "high": 33.12,
      "low": 33.04,
      "open": 33.12
    },
    "VESTL.IS": {
      "close": 29.74,
      "high": 29.8,
      "low": 29.7,
      "open": 29.8
    },
    "XAKUR.IS": {
      "close": 162518.16,
      "high": 162801.59,
      "low": 162488.77,
      "open": 162715.89
    },
    "XBANK.IS": {
      "close": 16508.59,
      "high": 16530.26,
      "low": 16500.71,
      "open": 16526.36
    },
    "XBLSM.IS": {
      "close": 6568.7,
      "high": 6569.93,
      "low": 6558.23,
      "open": 6559.15
    },
    "XELKT.IS": {
      "close": 739.13,
      "high": 740.17,
      "low": 739.13,
      "open": 740.17
    },
    "XFINK.IS": {
      "close": 50912.44,
      "high": 51024.87,
      "low": 50905.7,
      "open": 51022.9
    },
    "XGIDA.IS": {
      "close": 14050.96,
      "high": 14059.87,
      "low": 14046.25,
      "open": 14059.87
    },
    "XGMYO.IS": {
      "close": 6472.46,
      "high": 6486.41,
      "low": 6470.55,
      "open": 6486.41
    },
    "XHOLD.IS": {
      "close": 12550.33,
      "high": 12569.45,
      "low": 12550.33,
      "open": 12568.56
    },
    "XILTM.IS": {
      "close": 2787.1,
      "high": 2791.68,
      "low": 2782.52,
      "open": 2791.68
    },
    "XINSA.IS": {
      "close": 21706.68,
      "high": 21709.32,
      "low": 21681.32,
      "open": 21705.59
    },
    "XKAGT.IS": {
      "close": 7603.66,
      "high": 7613.4,
      "low": 7602.71,
      "open": 7610.27
    },
    "XKMYA.IS": {
      "close": 15861.58,
      "high": 15868.18,
      "low": 15842.75,
      "open": 15855.39
    },
    "XMADN.IS": {
      "close": 14058.18,
      "high": 14070.22,
      "low": 14032.23,
      "open": 14061.2
    },
    "XMANA.IS": {
      "close": 20982.32,
      "high": 20998.42,
      "low": 20971.61,
      "open": 20997.13
    },
    "XMESY.IS": {
      "close": 23402.74,
      "high": 23414.0,
      "low": 23387.04,
      "open": 23411.62
    },
    "XSGRT.IS": {
      "close": 79239.19,
      "high": 79265.28,
      "low": 79160.48,
      "open": 79258.62
    },
    "XSINS.IS": {
      "close": 16479.64,
      "high": 16484.84,
      "low": 16475.12,
      "open": 16484.84
    },
    "XSPOR.IS": {
      "close": 1790.4,
      "high": 1794.02,
      "low": 1784.84,
      "open": 1794.02
    },
    "XTAST.IS": {
      "close": 15281.85,
      "high": 15294.25,
      "low": 15273.55,
      "open": 15294.25
    },
    "XTCRT.IS": {
      "close": 30915.32,
      "high": 30945.62,
      "low": 30912.8,
      "open": 30939.14
    },
    "XTEKS.IS": {
      "close": 4857.05,
      "high": 4867.68,
      "low": 4852.68,
      "open": 4867.17
    },
    "XTRZM.IS": {
      "close": 1751.18,
      "high": 1751.76,
      "low": 1749.45,
      "open": 1749.53
    },
    "XU030.IS": {
      "close": 15010.08,
      "high": 15021.84,
      "low": 15004.63,
      "open": 15021.84
    },
    "XU050.IS": {
      "close": 11820.76,
      "high": 11831.06,
      "low": 11819.3,
      "open": 11831.06
    },
    "XU100.IS": {
      "close": 13140.38,
      "high": 13149.38,
      "low": 13136.34,
      "open": 13149.38
    },
    "XU500.IS": {
      "close": 16232.74,
      "high": 16245.19,
      "low": 16230.45,
      "open": 16245.19
    },
    "XUHIZ.IS": {
      "close": 11972.73,
      "high": 11984.83,
      "low": 11969.92,
      "open": 11984.83
    },
    "XULAS.IS": {
      "close": 36214.07,
      "high": 36279.12,
      "low": 36199.14,
      "open": 36275.11
    },
    "XUMAL.IS": {
      "close": 18087.87,
      "high": 18109.51,
      "low": 18087.87,
      "open": 18109.51
    },
    "XUSIN.IS": {
      "close": 16481.04,
      "high": 16485.38,
      "low": 16473.78,
      "open": 16484.84
    },
    "XUTEK.IS": {
      "close": 41896.32,
      "high": 41940.96,
      "low": 41862.76,
      "open": 41905.14
    },
    "XUTUM.IS": {
      "close": 16469.15,
      "high": 16482.41,
      "low": 16468.92,
      "open": 16482.41
    },
    "YEOTK.IS": {
      "close": 51.6,
      "high": 51.8,
      "low": 51.5,
      "open": 51.75
    },
    "YKBNK.IS": {
      "close": 34.58,
      "high": 34.66,
      "low": 34.52,
      "open": 34.66
    },
    "ZOREN.IS": {
      "close": 2.92,
      "high": 2.93,
      "low": 2.92,
      "open": 2.93
    }
  },
  "time": "2026-03-23T17:50",
  "updated_at": "2026-03-23T19:01"
}