{
  "data": {
    "AEFES.IS": {
      "close": 19.29,
      "high": 19.31,
      "low": 19.27,
      "open": 19.3,
      "tier": {
        "amount": 100000,
        "no": 2
      }
    },
    "AKBNK.IS": {
      "close": 81.8,
      "high": 81.8,
      "low": 81.7,
      "open": 81.75,
      "tier": {
        "amount": 200000,
        "no": 1
      }
    },
    "ASELS.IS": {
      "close": 401.75,
      "high": 402.75,
      "low": 401.25,
      "open": 402.5,
      "tier": {
        "amount": 200000,
        "no": 1
      }
    },
    "ASTOR.IS": {
      "close": 216.9,
      "high": 217.0,
      "low": 216.2,
      "open": 216.2,
      "tier": {
        "amount": 100000,
        "no": 2
      }
    },
    "BIMAS.IS": {
      "close": 757.5,
      "high": 758.0,
      "low": 757.0,
      "open": 758.0,
      "tier": {
        "amount": 40000,
        "no": 3
      }
    },
    "CIMSA.IS": {
      "close": 54.35,
      "high": 54.6,
      "low": 54.3,
      "open": 54.45,
      "tier": {
        "amount": 40000,
        "no": 3
      }
    },
    "EKGYO.IS": {
      "close": 21.5,
      "high": 21.5,
      "low": 21.46,
      "open": 21.48,
      "tier": {
        "amount": 100000,
        "no": 2
      }
    },
    "ENKAI.IS": {
      "close": 105.9,
      "high": 106.0,
      "low": 105.7,
      "open": 105.8,
      "tier": {
        "amount": 100000,
        "no": 2
      }
    },
    "EREGL.IS": {
      "close": 34.04,
      "high": 34.08,
      "low": 34.0,
      "open": 34.06,
      "tier": {
        "amount": 40000,
        "no": 3
      }
    },
    "FROTO.IS": {
      "close": 103.9,
      "high": 104.0,
      "low": 103.7,
      "open": 103.9,
      "tier": {
        "amount": 100000,
        "no": 2
      }
    },
    "GARAN.IS": {
      "close": 143.8,
      "high": 143.8,
      "low": 143.5,
      "open": 143.5,
      "tier": {
        "amount": 200000,
        "no": 1
      }
    },
    "GUBRF.IS": {
      "close": 518.5,
      "high": 519.0,
      "low": 518.5,
      "open": 519.0,
      "tier": {
        "amount": 40000,
        "no": 3
      }
    },
    "ISCTR.IS": {
      "close": 14.96,
      "high": 14.96,
      "low": 14.93,
      "open": 14.93,
      "tier": {
        "amount": 200000,
        "no": 1
      }
    },
    "KCHOL.IS": {
      "close": 207.1,
      "high": 207.2,
      "low": 206.9,
      "open": 207.0,
      "tier": {
        "amount": 200000,
        "no": 1
      }
    },
    "KRDMD.IS": {
      "close": 36.58,
      "high": 36.58,
      "low": 36.5,
      "open": 36.54,
      "tier": {
        "amount": 100000,
        "no": 2
      }
    },
    "MGROS.IS": {
      "close": 664.0,
      "high": 664.5,
      "low": 664.0,
      "open": 664.5,
      "tier": {
        "amount": 40000,
        "no": 3
      }
    },
    "PETKM.IS": {
      "close": 23.16,
      "high": 23.18,
      "low": 23.12,
      "open": 23.16,
      "tier": {
        "amount": 100000,
        "no": 2
      }
    },
    "PGSUS.IS": {
      "close": 191.8,
      "high": 191.9,
      "low": 191.7,
      "open": 191.8,
      "tier": {
        "amount": 100000,
        "no": 2
      }
    },
    "SAHOL.IS": {
      "close": 101.5,
      "high": 101.6,
      "low": 101.3,
      "open": 101.4,
      "tier": {
        "amount": 200000,
        "no": 1
      }
    },
    "SASA.IS": {
      "close": 3.07,
      "high": 3.07,
      "low": 3.06,
      "open": 3.07,
      "tier": {
        "amount": 40000,
        "no": 3
      }
    },
    "SISE.IS": {
      "close": 47.34,
      "high": 47.36,
      "low": 47.32,
      "open": 47.34,
      "tier": {
        "amount": 100000,
        "no": 2
      }
    },
    "TAVHL.IS": {
      "close": 312.5,
      "high": 312.5,
      "low": 312.0,
      "open": 312.0,
      "tier": {
        "amount": 40000,
        "no": 3
      }
    },
    "TCELL.IS": {
      "close": 116.2,
      "high": 116.2,
      "low": 115.9,
      "open": 116.2,
      "tier": {
        "amount": 200000,
        "no": 1
      }
    },
    "THYAO.IS": {
      "close": 330.25,
      "high": 330.25,
      "low": 329.75,
      "open": 330.0,
      "tier": {
        "amount": 200000,
        "no": 1
      }
    },
    "TOASO.IS": {
      "close": 289.5,
      "high": 289.5,
      "low": 288.5,
      "open": 288.75,
      "tier": {
        "amount": 40000,
        "no": 3
      }
    },
    "TTKOM.IS": {
      "close": 65.1,
      "high": 65.15,
      "low": 65.0,
      "open": 65.1,
      "tier": {
        "amount": 100000,
        "no": 2
      }
    },
    "TUPRS.IS": {
      "close": 255.25,
      "high": 256.0,
      "low": 254.75,
      "open": 255.75,
      "tier": {
        "amount": 200000,
        "no": 1
      }
    },
    "ULKER.IS": {
      "close": 123.8,
      "high": 123.9,
      "low": 123.5,
      "open": 123.6,
      "tier": {
        "amount": 40000,
        "no": 3
      }
    },
    "XBANK.IS": {
      "close": 18283.0,
      "high": 18285.23,
      "low": 18265.1,
      "open": 18266.94,
      "tier": {
        "amount": 0,
        "no": 0
      }
    },
    "XU030.IS": {
      "close": 16590.08,
      "high": 16591.88,
      "low": 16573.22,
      "open": 16588.62,
      "tier": {
        "amount": 0,
        "no": 0
      }
    },
    "XU100.IS": {
      "close": 14472.26,
      "high": 14473.79,
      "low": 14460.79,
      "open": 14470.08,
      "tier": {
        "amount": 0,
        "no": 0
      }
    },
    "YKBNK.IS": {
      "close": 38.92,
      "high": 38.94,
      "low": 38.9,
      "open": 38.9,
      "tier": {
        "amount": 200000,
        "no": 1
      }
    }
  },
  "time": "2026-04-21T16:40",
  "updated_at": "2026-04-21T17:01"
}