{
  "data": {
    "AEFES.IS": {
      "close": 17.75,
      "high": 17.81,
      "low": 17.75,
      "open": 17.78
    },
    "AGHOL.IS": {
      "close": 29.98,
      "high": 30.06,
      "low": 29.98,
      "open": 30.04
    },
    "AKBNK.IS": {
      "close": 76.95,
      "high": 77.25,
      "low": 76.9,
      "open": 77.1
    },
    "AKSA.IS": {
      "close": 10.29,
      "high": 10.29,
      "low": 10.25,
      "open": 10.26
    },
    "AKSEN.IS": {
      "close": 72.7,
      "high": 72.9,
      "low": 72.5,
      "open": 72.9
    },
    "ALARK.IS": {
      "close": 92.85,
      "high": 93.0,
      "low": 92.65,
      "open": 92.7
    },
    "ALTNY.IS": {
      "close": 15.27,
      "high": 15.3,
      "low": 15.27,
      "open": 15.28
    },
    "ANSGR.IS": {
      "close": 27.92,
      "high": 27.94,
      "low": 27.9,
      "open": 27.92
    },
    "ARCLK.IS": {
      "close": 113.1,
      "high": 114.0,
      "low": 113.0,
      "open": 113.8
    },
    "ASELS.IS": {
      "close": 332.5,
      "high": 333.75,
      "low": 332.25,
      "open": 332.75
    },
    "ASTOR.IS": {
      "close": 192.1,
      "high": 192.7,
      "low": 192.0,
      "open": 192.6
    },
    "BALSU.IS": {
      "close": 14.27,
      "high": 14.28,
      "low": 14.25,
      "open": 14.28
    },
    "BIMAS.IS": {
      "close": 682.0,
      "high": 683.0,
      "low": 680.5,
      "open": 681.5
    },
    "BRSAN.IS": {
      "close": 537.0,
      "high": 541.0,
      "low": 537.0,
      "open": 538.5
    },
    "BRYAT.IS": {
      "close": 2280.0,
      "high": 2288.0,
      "low": 2275.0,
      "open": 2286.0
    },
    "BSOKE.IS": {
      "close": 33.06,
      "high": 33.1,
      "low": 33.02,
      "open": 33.08
    },
    "BTCIM.IS": {
      "close": 5.82,
      "high": 5.85,
      "low": 5.82,
      "open": 5.84
    },
    "CANTE.IS": {
      "close": 1.52,
      "high": 1.52,
      "low": 1.51,
      "open": 1.52
    },
    "CCOLA.IS": {
      "close": 70.25,
      "high": 70.25,
      "low": 70.0,
      "open": 70.05
    },
    "CIMSA.IS": {
      "close": 48.76,
      "high": 49.04,
      "low": 48.74,
      "open": 49.02
    },
    "CWENE.IS": {
      "close": 29.24,
      "high": 29.3,
      "low": 29.22,
      "open": 29.26
    },
    "DAPGM.IS": {
      "close": 12.23,
      "high": 12.3,
      "low": 12.23,
      "open": 12.3
    },
    "DOAS.IS": {
      "close": 200.3,
      "high": 201.1,
      "low": 200.3,
      "open": 200.3
    },
    "DOHOL.IS": {
      "close": 21.44,
      "high": 21.52,
      "low": 21.38,
      "open": 21.5
    },
    "DSTKF.IS": {
      "close": 1782.0,
      "high": 1786.0,
      "low": 1778.0,
      "open": 1779.0
    },
    "ECILC.IS": {
      "close": 115.9,
      "high": 116.4,
      "low": 115.8,
      "open": 115.9
    },
    "EFOR.IS": {
      "close": 18.48,
      "high": 18.56,
      "low": 18.47,
      "open": 18.56
    },
    "EGEEN.IS": {
      "close": 5937.5,
      "high": 5950.0,
      "low": 5930.0,
      "open": 5942.5
    },
    "EKGYO.IS": {
      "close": 21.3,
      "high": 21.38,
      "low": 21.3,
      "open": 21.38
    },
    "ENERY.IS": {
      "close": 9.15,
      "high": 9.2,
      "low": 9.15,
      "open": 9.19
    },
    "ENJSA.IS": {
      "close": 113.7,
      "high": 114.1,
      "low": 113.5,
      "open": 113.9
    },
    "ENKAI.IS": {
      "close": 92.3,
      "high": 92.6,
      "low": 92.3,
      "open": 92.45
    },
    "EREGL.IS": {
      "close": 29.16,
      "high": 29.28,
      "low": 29.16,
      "open": 29.24
    },
    "EUPWR.IS": {
      "close": 36.34,
      "high": 36.5,
      "low": 36.34,
      "open": 36.46
    },
    "FENER.IS": {
      "close": 2.89,
      "high": 2.91,
      "low": 2.89,
      "open": 2.91
    },
    "FROTO.IS": {
      "close": 112.5,
      "high": 112.8,
      "low": 112.4,
      "open": 112.6
    },
    "GARAN.IS": {
      "close": 139.9,
      "high": 140.5,
      "low": 139.9,
      "open": 140.4
    },
    "GENIL.IS": {
      "close": 9.93,
      "high": 9.97,
      "low": 9.84,
      "open": 9.92
    },
    "GESAN.IS": {
      "close": 45.5,
      "high": 45.68,
      "low": 45.44,
      "open": 45.68
    },
    "GLRMK.IS": {
      "close": 159.8,
      "high": 160.4,
      "low": 159.7,
      "open": 160.1
    },
    "GRSEL.IS": {
      "close": 328.75,
      "high": 330.25,
      "low": 326.5,
      "open": 329.0
    },
    "GRTHO.IS": {
      "close": 256.25,
      "high": 257.0,
      "low": 255.75,
      "open": 257.0
    },
    "GSRAY.IS": {
      "close": 1.16,
      "high": 1.17,
      "low": 1.16,
      "open": 1.17
    },
    "GUBRF.IS": {
      "close": 518.5,
      "high": 520.0,
      "low": 517.0,
      "open": 520.0
    },
    "HALKB.IS": {
      "close": 49.34,
      "high": 49.44,
      "low": 49.32,
      "open": 49.42
    },
    "HEKTS.IS": {
      "close": 2.94,
      "high": 2.96,
      "low": 2.94,
      "open": 2.96
    },
    "ISCTR.IS": {
      "close": 14.61,
      "high": 14.68,
      "low": 14.6,
      "open": 14.67
    },
    "ISMEN.IS": {
      "close": 44.94,
      "high": 45.02,
      "low": 44.88,
      "open": 44.9
    },
    "IZENR.IS": {
      "close": 9.01,
      "high": 9.03,
      "low": 9.0,
      "open": 9.03
    },
    "KCAER.IS": {
      "close": 11.93,
      "high": 11.99,
      "low": 11.91,
      "open": 11.98
    },
    "KCHOL.IS": {
      "close": 192.8,
      "high": 193.2,
      "low": 192.8,
      "open": 193.0
    },
    "KLRHO.IS": {
      "close": 169.2,
      "high": 171.4,
      "low": 169.1,
      "open": 171.4
    },
    "KONTR.IS": {
      "close": 8.82,
      "high": 8.88,
      "low": 8.81,
      "open": 8.87
    },
    "KRDMD.IS": {
      "close": 31.48,
      "high": 31.66,
      "low": 31.46,
      "open": 31.62
    },
    "KTLEV.IS": {
      "close": 54.45,
      "high": 56.4,
      "low": 53.9,
      "open": 56.25
    },
    "KUYAS.IS": {
      "close": 72.05,
      "high": 72.15,
      "low": 71.8,
      "open": 71.95
    },
    "MAGEN.IS": {
      "close": 47.78,
      "high": 47.84,
      "low": 47.72,
      "open": 47.84
    },
    "MAVI.IS": {
      "close": 42.32,
      "high": 42.34,
      "low": 42.28,
      "open": 42.3
    },
    "MGROS.IS": {
      "close": 616.0,
      "high": 616.0,
      "low": 614.5,
      "open": 615.0
    },
    "MIATK.IS": {
      "close": 41.0,
      "high": 41.0,
      "low": 40.34,
      "open": 40.38
    },
    "MPARK.IS": {
      "close": 436.25,
      "high": 440.0,
      "low": 435.25,
      "open": 436.25
    },
    "OBAMS.IS": {
      "close": 7.8,
      "high": 7.85,
      "low": 7.8,
      "open": 7.84
    },
    "ODAS.IS": {
      "close": 6.12,
      "high": 6.14,
      "low": 6.12,
      "open": 6.12
    },
    "OTKAR.IS": {
      "close": 373.5,
      "high": 374.75,
      "low": 373.5,
      "open": 374.75
    },
    "OYAKC.IS": {
      "close": 23.3,
      "high": 23.4,
      "low": 23.3,
      "open": 23.38
    },
    "PASEU.IS": {
      "close": 116.2,
      "high": 116.8,
      "low": 116.1,
      "open": 116.8
    },
    "PATEK.IS": {
      "close": 17.74,
      "high": 17.83,
      "low": 17.72,
      "open": 17.82
    },
    "PETKM.IS": {
      "close": 17.95,
      "high": 18.01,
      "low": 17.93,
      "open": 17.98
    },
    "PGSUS.IS": {
      "close": 178.1,
      "high": 178.6,
      "low": 178.0,
      "open": 178.3
    },
    "QUAGR.IS": {
      "close": 2.88,
      "high": 2.9,
      "low": 2.88,
      "open": 2.89
    },
    "RALYH.IS": {
      "close": 138.6,
      "high": 139.0,
      "low": 138.5,
      "open": 139.0
    },
    "REEDR.IS": {
      "close": 6.29,
      "high": 6.33,
      "low": 6.28,
      "open": 6.32
    },
    "SAHOL.IS": {
      "close": 94.85,
      "high": 95.25,
      "low": 94.85,
      "open": 95.2
    },
    "SASA.IS": {
      "close": 2.23,
      "high": 2.25,
      "low": 2.23,
      "open": 2.25
    },
    "SISE.IS": {
      "close": 41.96,
      "high": 42.18,
      "low": 41.96,
      "open": 42.14
    },
    "SKBNK.IS": {
      "close": 10.44,
      "high": 10.49,
      "low": 10.42,
      "open": 10.47
    },
    "SOKM.IS": {
      "close": 59.65,
      "high": 59.75,
      "low": 59.55,
      "open": 59.65
    },
    "TABGD.IS": {
      "close": 254.25,
      "high": 255.25,
      "low": 253.75,
      "open": 255.25
    },
    "TAVHL.IS": {
      "close": 302.0,
      "high": 303.0,
      "low": 301.25,
      "open": 302.25
    },
    "TCELL.IS": {
      "close": 111.3,
      "high": 111.8,
      "low": 111.3,
      "open": 111.7
    },
    "THYAO.IS": {
      "close": 293.25,
      "high": 294.0,
      "low": 293.0,
      "open": 293.5
    },
    "TKFEN.IS": {
      "close": 83.6,
      "high": 84.75,
      "low": 83.15,
      "open": 83.25
    },
    "TOASO.IS": {
      "close": 302.0,
      "high": 303.0,
      "low": 301.0,
      "open": 301.0
    },
    "TRALT.IS": {
      "close": 54.9,
      "high": 55.2,
      "low": 54.8,
      "open": 54.8
    },
    "TRENJ.IS": {
      "close": 110.0,
      "high": 110.6,
      "low": 109.8,
      "open": 109.8
    },
    "TRMET.IS": {
      "close": 152.7,
      "high": 153.9,
      "low": 152.5,
      "open": 153.2
    },
    "TSKB.IS": {
      "close": 12.34,
      "high": 12.39,
      "low": 12.34,
      "open": 12.38
    },
    "TSPOR.IS": {
      "close": 1.0,
      "high": 1.02,
      "low": 1.0,
      "open": 1.02
    },
    "TTKOM.IS": {
      "close": 62.3,
      "high": 62.55,
      "low": 62.25,
      "open": 62.35
    },
    "TTRAK.IS": {
      "close": 450.75,
      "high": 451.75,
      "low": 450.25,
      "open": 451.5
    },
    "TUKAS.IS": {
      "close": 2.35,
      "high": 2.35,
      "low": 2.34,
      "open": 2.35
    },
    "TUPRS.IS": {
      "close": 251.0,
      "high": 252.25,
      "low": 250.75,
      "open": 251.5
    },
    "TUREX.IS": {
      "close": 6.98,
      "high": 7.02,
      "low": 6.98,
      "open": 7.0
    },
    "TURSG.IS": {
      "close": 12.15,
      "high": 12.17,
      "low": 12.14,
      "open": 12.15
    },
    "ULKER.IS": {
      "close": 113.0,
      "high": 113.6,
      "low": 113.0,
      "open": 113.3
    },
    "VAKBN.IS": {
      "close": 35.8,
      "high": 35.86,
      "low": 35.76,
      "open": 35.82
    },
    "VESTL.IS": {
      "close": 28.44,
      "high": 28.54,
      "low": 28.42,
      "open": 28.52
    },
    "XAKUR.IS": {
      "close": 155220.69,
      "high": 155462.7,
      "low": 155220.69,
      "open": 155308.44
    },
    "XBANK.IS": {
      "close": 17614.66,
      "high": 17689.68,
      "low": 17614.66,
      "open": 17676.13
    },
    "XBLSM.IS": {
      "close": 6207.03,
      "high": 6232.9,
      "low": 6205.13,
      "open": 6232.9
    },
    "XELKT.IS": {
      "close": 718.63,
      "high": 720.05,
      "low": 718.62,
      "open": 719.91
    },
    "XFINK.IS": {
      "close": 49076.98,
      "high": 49206.73,
      "low": 49019.4,
      "open": 49019.4
    },
    "XGIDA.IS": {
      "close": 14241.77,
      "high": 14249.57,
      "low": 14240.06,
      "open": 14248.87
    },
    "XGMYO.IS": {
      "close": 6317.6,
      "high": 6326.49,
      "low": 6317.6,
      "open": 6322.54
    },
    "XHOLD.IS": {
      "close": 12576.07,
      "high": 12601.76,
      "low": 12576.07,
      "open": 12601.3
    },
    "XILTM.IS": {
      "close": 2880.91,
      "high": 2889.46,
      "low": 2878.87,
      "open": 2887.54
    },
    "XINSA.IS": {
      "close": 20269.92,
      "high": 20308.37,
      "low": 20269.92,
      "open": 20289.61
    },
    "XKAGT.IS": {
      "close": 7344.05,
      "high": 7374.86,
      "low": 7343.2,
      "open": 7374.86
    },
    "XKMYA.IS": {
      "close": 15423.72,
      "high": 15475.12,
      "low": 15423.72,
      "open": 15466.59
    },
    "XMADN.IS": {
      "close": 16015.63,
      "high": 16094.21,
      "low": 16008.46,
      "open": 16014.17
    },
    "XMANA.IS": {
      "close": 21459.42,
      "high": 21535.91,
      "low": 21452.42,
      "open": 21530.2
    },
    "XMESY.IS": {
      "close": 23662.31,
      "high": 23715.22,
      "low": 23662.31,
      "open": 23691.0
    },
    "XSGRT.IS": {
      "close": 75443.59,
      "high": 75592.94,
      "low": 75417.99,
      "open": 75527.76
    },
    "XSINS.IS": {
      "close": 16563.45,
      "high": 16603.71,
      "low": 16563.45,
      "open": 16595.92
    },
    "XSPOR.IS": {
      "close": 1891.57,
      "high": 1903.25,
      "low": 1887.69,
      "open": 1899.62
    },
    "XTAST.IS": {
      "close": 15063.17,
      "high": 15099.27,
      "low": 15062.61,
      "open": 15096.52
    },
    "XTCRT.IS": {
      "close": 31009.08,
      "high": 31009.08,
      "low": 30952.09,
      "open": 30964.76
    },
    "XTEKS.IS": {
      "close": 4862.72,
      "high": 4869.52,
      "low": 4858.72,
      "open": 4866.3
    },
    "XTRZM.IS": {
      "close": 1800.6,
      "high": 1806.78,
      "low": 1799.25,
      "open": 1806.5
    },
    "XU030.IS": {
      "close": 15004.08,
      "high": 15049.97,
      "low": 15003.18,
      "open": 15032.35
    },
    "XU050.IS": {
      "close": 11849.35,
      "high": 11875.89,
      "low": 11846.76,
      "open": 11865.62
    },
    "XU100.IS": {
      "close": 13179.49,
      "high": 13218.43,
      "low": 13179.49,
      "open": 13208.02
    },
    "XU500.IS": {
      "close": 16162.78,
      "high": 16204.2,
      "low": 16162.78,
      "open": 16194.73
    },
    "XUHIZ.IS": {
      "close": 11820.15,
      "high": 11836.78,
      "low": 11813.66,
      "open": 11830.05
    },
    "XULAS.IS": {
      "close": 35999.11,
      "high": 36096.25,
      "low": 35981.04,
      "open": 36072.62
    },
    "XUMAL.IS": {
      "close": 18208.31,
      "high": 18256.34,
      "low": 18208.31,
      "open": 18251.82
    },
    "XUSIN.IS": {
      "close": 16557.49,
      "high": 16607.2,
      "low": 16557.49,
      "open": 16595.92
    },
    "XUTEK.IS": {
      "close": 39521.23,
      "high": 39659.53,
      "low": 39496.08,
      "open": 39580.89
    },
    "XUTUM.IS": {
      "close": 16383.68,
      "high": 16420.42,
      "low": 16382.62,
      "open": 16412.97
    },
    "YEOTK.IS": {
      "close": 46.26,
      "high": 46.26,
      "low": 46.26,
      "open": 46.26
    },
    "YKBNK.IS": {
      "close": 36.78,
      "high": 37.0,
      "low": 36.78,
      "open": 36.96
    },
    "ZOREN.IS": {
      "close": 2.99,
      "high": 2.99,
      "low": 2.98,
      "open": 2.99
    }
  },
  "time": "2026-03-11T10:30",
  "updated_at": "2026-03-11T10:53"
}