{
  "updated_at": "2026-04-13T23:51:05.042480",
  "indexes": [
    {
      "id": 1,
      "ticker": "XBANK.IS",
      "name": "XBANK.IS",
      "close": 17832.0,
      "open": 17441.9,
      "high": 17866.2,
      "low": 17420.3,
      "pivots": {
        "daily": 17706.167,
        "monthly": 17050.87,
        "monthlyP": 4.58
      },
      "rsi": 59.45,
      "ema": {
        "EMA_5": 17073.1,
        "EMA_8": 16790.72,
        "EMA_10": 16696.22,
        "EMA_13": 16645.11,
        "EMA_20": 16738.7,
        "EMA_21": 16762.62,
        "EMA_34": 17069.73,
        "EMA_50": 17266.07,
        "EMA_55": 17290.25
      },
      "bb": {
        "upper": 17726.31,
        "mid": 16373.33,
        "lower": 15020.36
      }
    },
    {
      "id": 2,
      "ticker": "XU030.IS",
      "name": "XU030.IS",
      "close": 16188.9,
      "open": 15812.2,
      "high": 16188.9,
      "low": 15792.2,
      "pivots": {
        "daily": 16056.667,
        "monthly": 15644.4,
        "monthlyP": 3.48
      },
      "rsi": 68.84,
      "ema": {
        "EMA_5": 15567.35,
        "EMA_8": 15343.38,
        "EMA_10": 15251.03,
        "EMA_13": 15161.29,
        "EMA_20": 15060.37,
        "EMA_21": 15051.42,
        "EMA_34": 14945.34,
        "EMA_50": 14767.0,
        "EMA_55": 14703.02
      },
      "bb": {
        "upper": 15783.93,
        "mid": 14914.92,
        "lower": 14045.91
      }
    },
    {
      "id": 3,
      "ticker": "XU100.IS",
      "name": "XU100.IS",
      "close": 14073.8,
      "open": 13774.5,
      "high": 14073.8,
      "low": 13763.8,
      "pivots": {
        "daily": 13970.466,
        "monthly": 13656.17,
        "monthlyP": 3.06
      },
      "rsi": 67.21,
      "ema": {
        "EMA_5": 13579.17,
        "EMA_8": 13405.57,
        "EMA_10": 13335.58,
        "EMA_13": 13270.98,
        "EMA_20": 13215.12,
        "EMA_21": 13212.21,
        "EMA_34": 13184.63,
        "EMA_50": 13097.62,
        "EMA_55": 13059.43
      },
      "bb": {
        "upper": 13754.23,
        "mid": 13079.73,
        "lower": 12405.22
      }
    },
    {
      "id": 4,
      "ticker": "XUSIN.IS",
      "name": "XUSIN.IS",
      "close": 17169.5,
      "open": 16908.8,
      "high": 17169.5,
      "low": 16908.8,
      "pivots": {
        "daily": 17082.6,
        "monthly": 16868.37,
        "monthlyP": 1.79
      },
      "rsi": 64.04,
      "ema": {
        "EMA_5": 16804.8,
        "EMA_8": 16679.42,
        "EMA_10": 16626.66,
        "EMA_13": 16575.3,
        "EMA_20": 16519.01,
        "EMA_21": 16514.06,
        "EMA_34": 16445.32,
        "EMA_50": 16307.18,
        "EMA_55": 16255.88
      },
      "bb": {
        "upper": 17006.45,
        "mid": 16441.94,
        "lower": 15877.43
      }
    }
  ],
  "stocks": [
    {
      "id": 1,
      "ticker": "AEFES.IS",
      "name": "AEFES.IS",
      "close": 19.3,
      "open": 18.01,
      "high": 19.37,
      "low": 17.85,
      "pivots": {
        "daily": 18.84,
        "monthly": 18.39,
        "monthlyP": 4.93
      },
      "rsi": 63.15,
      "ema": {
        "EMA_5": 18.01,
        "EMA_8": 17.73,
        "EMA_10": 17.63,
        "EMA_13": 17.57,
        "EMA_20": 17.6,
        "EMA_21": 17.61,
        "EMA_34": 17.79,
        "EMA_50": 17.84,
        "EMA_55": 17.83
      },
      "bb": {
        "upper": 18.53,
        "mid": 17.33,
        "lower": 16.13
      }
    },
    {
      "id": 2,
      "ticker": "AGHOL.IS",
      "name": "AGHOL.IS",
      "close": 30.84,
      "open": 29.26,
      "high": 30.9,
      "low": 29.2,
      "pivots": {
        "daily": 30.313,
        "monthly": 29.7,
        "monthlyP": 3.84
      },
      "rsi": 59.97,
      "ema": {
        "EMA_5": 29.31,
        "EMA_8": 28.91,
        "EMA_10": 28.79,
        "EMA_13": 28.73,
        "EMA_20": 28.94,
        "EMA_21": 28.99,
        "EMA_34": 29.62,
        "EMA_50": 30.08,
        "EMA_55": 30.16
      },
      "bb": {
        "upper": 30.2,
        "mid": 28.34,
        "lower": 26.49
      }
    },
    {
      "id": 3,
      "ticker": "AKBNK.IS",
      "name": "AKBNK.IS",
      "close": 78.4,
      "open": 76.0,
      "high": 78.5,
      "low": 75.85,
      "pivots": {
        "daily": 77.583,
        "monthly": 74.45,
        "monthlyP": 5.31
      },
      "rsi": 61.8,
      "ema": {
        "EMA_5": 74.55,
        "EMA_8": 73.05,
        "EMA_10": 72.49,
        "EMA_13": 72.1,
        "EMA_20": 72.24,
        "EMA_21": 72.32,
        "EMA_34": 73.37,
        "EMA_50": 73.91,
        "EMA_55": 73.91
      },
      "bb": {
        "upper": 76.98,
        "mid": 70.37,
        "lower": 63.77
      }
    },
    {
      "id": 4,
      "ticker": "AKSA.IS",
      "name": "AKSA.IS",
      "close": 10.3,
      "open": 10.26,
      "high": 10.35,
      "low": 10.21,
      "pivots": {
        "daily": 10.287,
        "monthly": 10.49,
        "monthlyP": -1.84
      },
      "rsi": 51.0,
      "ema": {
        "EMA_5": 10.28,
        "EMA_8": 10.31,
        "EMA_10": 10.31,
        "EMA_13": 10.31,
        "EMA_20": 10.29,
        "EMA_21": 10.28,
        "EMA_34": 10.22,
        "EMA_50": 10.17,
        "EMA_55": 10.16
      },
      "bb": {
        "upper": 10.75,
        "mid": 10.38,
        "lower": 10.02
      }
    },
    {
      "id": 5,
      "ticker": "AKSEN.IS",
      "name": "AKSEN.IS",
      "close": 81.3,
      "open": 81.25,
      "high": 82.15,
      "low": 79.6,
      "pivots": {
        "daily": 81.017,
        "monthly": 80.75,
        "monthlyP": 0.68
      },
      "rsi": 61.5,
      "ema": {
        "EMA_5": 80.61,
        "EMA_8": 79.91,
        "EMA_10": 79.47,
        "EMA_13": 78.86,
        "EMA_20": 77.61,
        "EMA_21": 77.45,
        "EMA_34": 75.66,
        "EMA_50": 73.77,
        "EMA_55": 73.19
      },
      "bb": {
        "upper": 82.73,
        "mid": 77.88,
        "lower": 73.04
      }
    },
    {
      "id": 6,
      "ticker": "ALARK.IS",
      "name": "ALARK.IS",
      "close": 93.95,
      "open": 92.0,
      "high": 94.0,
      "low": 90.95,
      "pivots": {
        "daily": 92.967,
        "monthly": 91.72,
        "monthlyP": 2.44
      },
      "rsi": 53.24,
      "ema": {
        "EMA_5": 91.35,
        "EMA_8": 90.73,
        "EMA_10": 90.56,
        "EMA_13": 90.57,
        "EMA_20": 91.36,
        "EMA_21": 91.52,
        "EMA_34": 93.65,
        "EMA_50": 95.43,
        "EMA_55": 95.78
      },
      "bb": {
        "upper": 92.99,
        "mid": 89.68,
        "lower": 86.37
      }
    },
    {
      "id": 7,
      "ticker": "ALTNY.IS",
      "name": "ALTNY.IS",
      "close": 15.22,
      "open": 14.76,
      "high": 15.39,
      "low": 14.73,
      "pivots": {
        "daily": 15.113,
        "monthly": 15.15,
        "monthlyP": 0.46
      },
      "rsi": 52.13,
      "ema": {
        "EMA_5": 14.95,
        "EMA_8": 14.87,
        "EMA_10": 14.85,
        "EMA_13": 14.86,
        "EMA_20": 14.96,
        "EMA_21": 14.98,
        "EMA_34": 15.2,
        "EMA_50": 15.38,
        "EMA_55": 15.42
      },
      "bb": {
        "upper": 15.37,
        "mid": 14.78,
        "lower": 14.19
      }
    },
    {
      "id": 8,
      "ticker": "ANSGR.IS",
      "name": "ANSGR.IS",
      "close": 27.0,
      "open": 26.66,
      "high": 27.0,
      "low": 26.52,
      "pivots": {
        "daily": 26.84,
        "monthly": 26.7,
        "monthlyP": 1.12
      },
      "rsi": 61.95,
      "ema": {
        "EMA_5": 26.53,
        "EMA_8": 26.37,
        "EMA_10": 26.31,
        "EMA_13": 26.24,
        "EMA_20": 26.13,
        "EMA_21": 26.11,
        "EMA_34": 25.91,
        "EMA_50": 25.62,
        "EMA_55": 25.52
      },
      "bb": {
        "upper": 27.26,
        "mid": 26.22,
        "lower": 25.17
      }
    },
    {
      "id": 9,
      "ticker": "ARCLK.IS",
      "name": "ARCLK.IS",
      "close": 117.3,
      "open": 116.6,
      "high": 118.3,
      "low": 115.2,
      "pivots": {
        "daily": 116.933,
        "monthly": 114.17,
        "monthlyP": 2.74
      },
      "rsi": 57.95,
      "ema": {
        "EMA_5": 113.21,
        "EMA_8": 112.35,
        "EMA_10": 112.13,
        "EMA_13": 112.04,
        "EMA_20": 112.34,
        "EMA_21": 112.41,
        "EMA_34": 113.17,
        "EMA_50": 113.62,
        "EMA_55": 113.7
      },
      "bb": {
        "upper": 117.83,
        "mid": 112.16,
        "lower": 106.48
      }
    },
    {
      "id": 10,
      "ticker": "ASELS.IS",
      "name": "ASELS.IS",
      "close": 398.5,
      "open": 377.0,
      "high": 399.5,
      "low": 376.5,
      "pivots": {
        "daily": 391.5,
        "monthly": 371.92,
        "monthlyP": 7.15
      },
      "rsi": 73.09,
      "ema": {
        "EMA_5": 369.59,
        "EMA_8": 359.59,
        "EMA_10": 355.44,
        "EMA_13": 351.05,
        "EMA_20": 344.34,
        "EMA_21": 343.55,
        "EMA_34": 334.23,
        "EMA_50": 322.98,
        "EMA_55": 319.5
      },
      "bb": {
        "upper": 380.61,
        "mid": 341.38,
        "lower": 302.14
      }
    },
    {
      "id": 11,
      "ticker": "ASTOR.IS",
      "name": "ASTOR.IS",
      "close": 206.5,
      "open": 209.0,
      "high": 212.2,
      "low": 206.1,
      "pivots": {
        "daily": 208.267,
        "monthly": 205.7,
        "monthlyP": 0.39
      },
      "rsi": 59.11,
      "ema": {
        "EMA_5": 206.13,
        "EMA_8": 205.09,
        "EMA_10": 204.22,
        "EMA_13": 202.84,
        "EMA_20": 199.51,
        "EMA_21": 199.03,
        "EMA_34": 192.48,
        "EMA_50": 184.11,
        "EMA_55": 181.56
      },
      "bb": {
        "upper": 216.33,
        "mid": 198.8,
        "lower": 181.28
      }
    },
    {
      "id": 12,
      "ticker": "BALSU.IS",
      "name": "BALSU.IS",
      "close": 14.85,
      "open": 14.96,
      "high": 14.96,
      "low": 14.7,
      "pivots": {
        "daily": 14.837,
        "monthly": 15.0,
        "monthlyP": -0.98
      },
      "rsi": 52.48,
      "ema": {
        "EMA_5": 14.79,
        "EMA_8": 14.71,
        "EMA_10": 14.66,
        "EMA_13": 14.62,
        "EMA_20": 14.61,
        "EMA_21": 14.62,
        "EMA_34": 14.82,
        "EMA_50": 15.15,
        "EMA_55": 15.26
      },
      "bb": {
        "upper": 15.06,
        "mid": 14.39,
        "lower": 13.72
      }
    },
    {
      "id": 13,
      "ticker": "BIMAS.IS",
      "name": "BIMAS.IS",
      "close": 751.0,
      "open": 744.0,
      "high": 751.5,
      "low": 734.5,
      "pivots": {
        "daily": 745.667,
        "monthly": 727.83,
        "monthlyP": 3.18
      },
      "rsi": 66.98,
      "ema": {
        "EMA_5": 726.3,
        "EMA_8": 716.06,
        "EMA_10": 711.47,
        "EMA_13": 706.39,
        "EMA_20": 698.72,
        "EMA_21": 697.86,
        "EMA_34": 688.09,
        "EMA_50": 676.03,
        "EMA_55": 672.21
      },
      "bb": {
        "upper": 737.36,
        "mid": 695.08,
        "lower": 652.79
      }
    },
    {
      "id": 14,
      "ticker": "BRSAN.IS",
      "name": "BRSAN.IS",
      "close": 543.5,
      "open": 539.0,
      "high": 546.0,
      "low": 535.0,
      "pivots": {
        "daily": 541.5,
        "monthly": 531.33,
        "monthlyP": 2.29
      },
      "rsi": 51.39,
      "ema": {
        "EMA_5": 529.8,
        "EMA_8": 526.38,
        "EMA_10": 525.29,
        "EMA_13": 525.26,
        "EMA_20": 530.77,
        "EMA_21": 531.92,
        "EMA_34": 547.07,
        "EMA_50": 557.73,
        "EMA_55": 559.15
      },
      "bb": {
        "upper": 537.02,
        "mid": 517.01,
        "lower": 497.01
      }
    },
    {
      "id": 15,
      "ticker": "BRYAT.IS",
      "name": "BRYAT.IS",
      "close": 2148.0,
      "open": 2150.0,
      "high": 2165.0,
      "low": 2142.0,
      "pivots": {
        "daily": 2151.667,
        "monthly": 2099.1,
        "monthlyP": 2.33
      },
      "rsi": 58.7,
      "ema": {
        "EMA_5": 2103.26,
        "EMA_8": 2076.61,
        "EMA_10": 2065.84,
        "EMA_13": 2057.03,
        "EMA_20": 2054.75,
        "EMA_21": 2055.45,
        "EMA_34": 2068.98,
        "EMA_50": 2082.2,
        "EMA_55": 2085.03
      },
      "bb": {
        "upper": 2165.26,
        "mid": 2028.18,
        "lower": 1891.09
      }
    },
    {
      "id": 16,
      "ticker": "BSOKE.IS",
      "name": "BSOKE.IS",
      "close": 35.5,
      "open": 36.0,
      "high": 36.64,
      "low": 35.34,
      "pivots": {
        "daily": 35.827,
        "monthly": 34.83,
        "monthlyP": 1.91
      },
      "rsi": 67.12,
      "ema": {
        "EMA_5": 35.01,
        "EMA_8": 34.63,
        "EMA_10": 34.44,
        "EMA_13": 34.19,
        "EMA_20": 33.64,
        "EMA_21": 33.57,
        "EMA_34": 32.44,
        "EMA_50": 30.93,
        "EMA_55": 30.47
      },
      "bb": {
        "upper": 35.48,
        "mid": 33.73,
        "lower": 31.97
      }
    },
    {
      "id": 17,
      "ticker": "BTCIM.IS",
      "name": "BTCIM.IS",
      "close": 6.58,
      "open": 6.6,
      "high": 6.68,
      "low": 6.55,
      "pivots": {
        "daily": 6.603,
        "monthly": 6.4,
        "monthlyP": 2.81
      },
      "rsi": 60.76,
      "ema": {
        "EMA_5": 6.48,
        "EMA_8": 6.43,
        "EMA_10": 6.4,
        "EMA_13": 6.37,
        "EMA_20": 6.27,
        "EMA_21": 6.25,
        "EMA_34": 6.02,
        "EMA_50": 5.76,
        "EMA_55": 5.69
      },
      "bb": {
        "upper": 6.94,
        "mid": 6.42,
        "lower": 5.9
      }
    },
    {
      "id": 18,
      "ticker": "CANTE.IS",
      "name": "CANTE.IS",
      "close": 1.67,
      "open": 1.65,
      "high": 1.69,
      "low": 1.63,
      "pivots": {
        "daily": 1.663,
        "monthly": 1.66,
        "monthlyP": 0.4
      },
      "rsi": 52.47,
      "ema": {
        "EMA_5": 1.66,
        "EMA_8": 1.65,
        "EMA_10": 1.65,
        "EMA_13": 1.65,
        "EMA_20": 1.64,
        "EMA_21": 1.64,
        "EMA_34": 1.66,
        "EMA_50": 1.7,
        "EMA_55": 1.72
      },
      "bb": {
        "upper": 1.73,
        "mid": 1.63,
        "lower": 1.53
      }
    },
    {
      "id": 19,
      "ticker": "CCOLA.IS",
      "name": "CCOLA.IS",
      "close": 73.5,
      "open": 71.3,
      "high": 73.5,
      "low": 71.05,
      "pivots": {
        "daily": 72.683,
        "monthly": 70.98,
        "monthlyP": 3.55
      },
      "rsi": 58.4,
      "ema": {
        "EMA_5": 70.77,
        "EMA_8": 70.1,
        "EMA_10": 69.91,
        "EMA_13": 69.81,
        "EMA_20": 69.88,
        "EMA_21": 69.91,
        "EMA_34": 70.05,
        "EMA_50": 69.6,
        "EMA_55": 69.34
      },
      "bb": {
        "upper": 73.65,
        "mid": 69.69,
        "lower": 65.74
      }
    },
    {
      "id": 20,
      "ticker": "CIMSA.IS",
      "name": "CIMSA.IS",
      "close": 53.35,
      "open": 52.5,
      "high": 53.7,
      "low": 52.1,
      "pivots": {
        "daily": 53.05,
        "monthly": 51.69,
        "monthlyP": 3.21
      },
      "rsi": 63.12,
      "ema": {
        "EMA_5": 51.7,
        "EMA_8": 51.01,
        "EMA_10": 50.7,
        "EMA_13": 50.37,
        "EMA_20": 49.97,
        "EMA_21": 49.93,
        "EMA_34": 49.64,
        "EMA_50": 49.33,
        "EMA_55": 49.24
      },
      "bb": {
        "upper": 52.42,
        "mid": 49.46,
        "lower": 46.5
      }
    },
    {
      "id": 21,
      "ticker": "CWENE.IS",
      "name": "CWENE.IS",
      "close": 32.92,
      "open": 32.88,
      "high": 34.0,
      "low": 32.56,
      "pivots": {
        "daily": 33.16,
        "monthly": 31.85,
        "monthlyP": 3.37
      },
      "rsi": 64.3,
      "ema": {
        "EMA_5": 31.77,
        "EMA_8": 31.23,
        "EMA_10": 30.98,
        "EMA_13": 30.71,
        "EMA_20": 30.39,
        "EMA_21": 30.36,
        "EMA_34": 30.2,
        "EMA_50": 30.02,
        "EMA_55": 29.93
      },
      "bb": {
        "upper": 32.29,
        "mid": 29.92,
        "lower": 27.54
      }
    },
    {
      "id": 22,
      "ticker": "DAPGM.IS",
      "name": "DAPGM.IS",
      "close": 11.65,
      "open": 11.7,
      "high": 11.96,
      "low": 11.12,
      "pivots": {
        "daily": 11.577,
        "monthly": 12.54,
        "monthlyP": -7.1
      },
      "rsi": 36.02,
      "ema": {
        "EMA_5": 12.41,
        "EMA_8": 12.85,
        "EMA_10": 13.03,
        "EMA_13": 13.19,
        "EMA_20": 13.29,
        "EMA_21": 13.28,
        "EMA_34": 13.13,
        "EMA_50": 12.94,
        "EMA_55": 12.9
      },
      "bb": {
        "upper": 16.15,
        "mid": 14.0,
        "lower": 11.85
      }
    },
    {
      "id": 23,
      "ticker": "DOAS.IS",
      "name": "DOAS.IS",
      "close": 189.1,
      "open": 189.47,
      "high": 190.68,
      "low": 187.25,
      "pivots": {
        "daily": 189.007,
        "monthly": 185.27,
        "monthlyP": 2.07
      },
      "rsi": 55.02,
      "ema": {
        "EMA_5": 184.71,
        "EMA_8": 183.28,
        "EMA_10": 182.83,
        "EMA_13": 182.65,
        "EMA_20": 183.53,
        "EMA_21": 183.73,
        "EMA_34": 186.48,
        "EMA_50": 188.41,
        "EMA_55": 188.66
      },
      "bb": {
        "upper": 189.37,
        "mid": 181.6,
        "lower": 173.82
      }
    },
    {
      "id": 24,
      "ticker": "DOHOL.IS",
      "name": "DOHOL.IS",
      "close": 21.08,
      "open": 20.74,
      "high": 21.26,
      "low": 20.72,
      "pivots": {
        "daily": 21.02,
        "monthly": 20.51,
        "monthlyP": 2.78
      },
      "rsi": 55.63,
      "ema": {
        "EMA_5": 20.53,
        "EMA_8": 20.42,
        "EMA_10": 20.41,
        "EMA_13": 20.42,
        "EMA_20": 20.47,
        "EMA_21": 20.48,
        "EMA_34": 20.5,
        "EMA_50": 20.39,
        "EMA_55": 20.34
      },
      "bb": {
        "upper": 21.71,
        "mid": 20.58,
        "lower": 19.45
      }
    },
    {
      "id": 25,
      "ticker": "DSTKF.IS",
      "name": "DSTKF.IS",
      "close": 2097.0,
      "open": 2036.0,
      "high": 2131.0,
      "low": 1995.0,
      "pivots": {
        "daily": 2074.333,
        "monthly": 2036.67,
        "monthlyP": 2.96
      },
      "rsi": 85.45,
      "ema": {
        "EMA_5": 2016.65,
        "EMA_8": 1986.59,
        "EMA_10": 1968.97,
        "EMA_13": 1942.81,
        "EMA_20": 1875.47,
        "EMA_21": 1865.09,
        "EMA_34": 1725.56,
        "EMA_50": 1570.61,
        "EMA_55": 1528.49
      },
      "bb": {
        "upper": 2066.26,
        "mid": 1891.55,
        "lower": 1716.84
      }
    },
    {
      "id": 26,
      "ticker": "ECILC.IS",
      "name": "ECILC.IS",
      "close": 110.4,
      "open": 109.6,
      "high": 111.3,
      "low": 109.2,
      "pivots": {
        "daily": 110.3,
        "monthly": 108.8,
        "monthlyP": 1.47
      },
      "rsi": 48.47,
      "ema": {
        "EMA_5": 108.84,
        "EMA_8": 108.81,
        "EMA_10": 109.05,
        "EMA_13": 109.53,
        "EMA_20": 110.67,
        "EMA_21": 110.8,
        "EMA_34": 111.69,
        "EMA_50": 111.08,
        "EMA_55": 110.66
      },
      "bb": {
        "upper": 122.38,
        "mid": 111.92,
        "lower": 101.45
      }
    },
    {
      "id": 27,
      "ticker": "EFOR.IS",
      "name": "EFOR.IS",
      "close": 5.34,
      "open": 5.97,
      "high": 5.98,
      "low": 5.34,
      "pivots": {
        "daily": 5.553,
        "monthly": 6.95,
        "monthlyP": -23.13
      },
      "rsi": 13.18,
      "ema": {
        "EMA_5": 6.3,
        "EMA_8": 6.96,
        "EMA_10": 7.42,
        "EMA_13": 8.14,
        "EMA_20": 9.81,
        "EMA_21": 10.03,
        "EMA_34": 12.6,
        "EMA_50": 14.87,
        "EMA_55": 15.42
      },
      "bb": {
        "upper": 15.74,
        "mid": 9.63,
        "lower": 3.52
      }
    },
    {
      "id": 28,
      "ticker": "EGEEN.IS",
      "name": "EGEEN.IS",
      "close": 5737.5,
      "open": 5552.5,
      "high": 5742.5,
      "low": 5552.5,
      "pivots": {
        "daily": 5677.5,
        "monthly": 5630.83,
        "monthlyP": 1.89
      },
      "rsi": 46.26,
      "ema": {
        "EMA_5": 5615.24,
        "EMA_8": 5602.26,
        "EMA_10": 5607.78,
        "EMA_13": 5630.05,
        "EMA_20": 5723.08,
        "EMA_21": 5739.17,
        "EMA_34": 5963.18,
        "EMA_50": 6212.47,
        "EMA_55": 6280.12
      },
      "bb": {
        "upper": 5953.57,
        "mid": 5658.62,
        "lower": 5363.68
      }
    },
    {
      "id": 29,
      "ticker": "EKGYO.IS",
      "name": "EKGYO.IS",
      "close": 21.54,
      "open": 20.82,
      "high": 21.58,
      "low": 20.68,
      "pivots": {
        "daily": 21.267,
        "monthly": 20.75,
        "monthlyP": 3.82
      },
      "rsi": 56.96,
      "ema": {
        "EMA_5": 20.59,
        "EMA_8": 20.34,
        "EMA_10": 20.26,
        "EMA_13": 20.24,
        "EMA_20": 20.42,
        "EMA_21": 20.45,
        "EMA_34": 20.92,
        "EMA_50": 21.27,
        "EMA_55": 21.33
      },
      "bb": {
        "upper": 21.2,
        "mid": 20.0,
        "lower": 18.81
      }
    },
    {
      "id": 30,
      "ticker": "ENERY.IS",
      "name": "ENERY.IS",
      "close": 8.94,
      "open": 8.98,
      "high": 9.44,
      "low": 8.88,
      "pivots": {
        "daily": 9.087,
        "monthly": 8.93,
        "monthlyP": 0.15
      },
      "rsi": 51.92,
      "ema": {
        "EMA_5": 8.76,
        "EMA_8": 8.71,
        "EMA_10": 8.71,
        "EMA_13": 8.72,
        "EMA_20": 8.78,
        "EMA_21": 8.8,
        "EMA_34": 8.95,
        "EMA_50": 9.1,
        "EMA_55": 9.13
      },
      "bb": {
        "upper": 9.07,
        "mid": 8.69,
        "lower": 8.31
      }
    },
    {
      "id": 31,
      "ticker": "ENJSA.IS",
      "name": "ENJSA.IS",
      "close": 119.52,
      "open": 117.7,
      "high": 120.0,
      "low": 117.12,
      "pivots": {
        "daily": 118.881,
        "monthly": 116.71,
        "monthlyP": 2.41
      },
      "rsi": 62.34,
      "ema": {
        "EMA_5": 116.81,
        "EMA_8": 115.7,
        "EMA_10": 115.16,
        "EMA_13": 114.47,
        "EMA_20": 113.06,
        "EMA_21": 112.86,
        "EMA_34": 110.39,
        "EMA_50": 107.39,
        "EMA_55": 106.48
      },
      "bb": {
        "upper": 119.89,
        "mid": 113.88,
        "lower": 107.87
      }
    },
    {
      "id": 32,
      "ticker": "ENKAI.IS",
      "name": "ENKAI.IS",
      "close": 102.2,
      "open": 95.55,
      "high": 102.3,
      "low": 95.3,
      "pivots": {
        "daily": 99.933,
        "monthly": 98.32,
        "monthlyP": 3.94
      },
      "rsi": 66.78,
      "ema": {
        "EMA_5": 96.46,
        "EMA_8": 95.13,
        "EMA_10": 94.61,
        "EMA_13": 94.1,
        "EMA_20": 93.53,
        "EMA_21": 93.48,
        "EMA_34": 92.79,
        "EMA_50": 91.56,
        "EMA_55": 91.12
      },
      "bb": {
        "upper": 98.13,
        "mid": 92.86,
        "lower": 87.59
      }
    },
    {
      "id": 33,
      "ticker": "EREGL.IS",
      "name": "EREGL.IS",
      "close": 31.3,
      "open": 30.28,
      "high": 31.32,
      "low": 30.16,
      "pivots": {
        "daily": 30.927,
        "monthly": 30.19,
        "monthlyP": 3.69
      },
      "rsi": 62.53,
      "ema": {
        "EMA_5": 30.09,
        "EMA_8": 29.67,
        "EMA_10": 29.49,
        "EMA_13": 29.3,
        "EMA_20": 29.1,
        "EMA_21": 29.08,
        "EMA_34": 28.9,
        "EMA_50": 28.63,
        "EMA_55": 28.55
      },
      "bb": {
        "upper": 30.61,
        "mid": 28.62,
        "lower": 26.63
      }
    },
    {
      "id": 34,
      "ticker": "EUPWR.IS",
      "name": "EUPWR.IS",
      "close": 44.36,
      "open": 43.6,
      "high": 44.64,
      "low": 43.06,
      "pivots": {
        "daily": 44.02,
        "monthly": 42.91,
        "monthlyP": 3.37
      },
      "rsi": 69.41,
      "ema": {
        "EMA_5": 42.74,
        "EMA_8": 41.9,
        "EMA_10": 41.41,
        "EMA_13": 40.81,
        "EMA_20": 39.84,
        "EMA_21": 39.74,
        "EMA_34": 38.9,
        "EMA_50": 38.23,
        "EMA_55": 38.03
      },
      "bb": {
        "upper": 44.99,
        "mid": 38.66,
        "lower": 32.33
      }
    },
    {
      "id": 35,
      "ticker": "FENER.IS",
      "name": "FENER.IS",
      "close": 2.76,
      "open": 2.74,
      "high": 2.76,
      "low": 2.73,
      "pivots": {
        "daily": 2.75,
        "monthly": 2.75,
        "monthlyP": 0.49
      },
      "rsi": 45.99,
      "ema": {
        "EMA_5": 2.75,
        "EMA_8": 2.73,
        "EMA_10": 2.73,
        "EMA_13": 2.73,
        "EMA_20": 2.76,
        "EMA_21": 2.77,
        "EMA_34": 2.93,
        "EMA_50": 3.3,
        "EMA_55": 3.45
      },
      "bb": {
        "upper": 2.88,
        "mid": 2.71,
        "lower": 2.54
      }
    },
    {
      "id": 36,
      "ticker": "FROTO.IS",
      "name": "FROTO.IS",
      "close": 105.3,
      "open": 103.0,
      "high": 105.3,
      "low": 102.3,
      "pivots": {
        "daily": 104.3,
        "monthly": 102.38,
        "monthlyP": 2.85
      },
      "rsi": 51.82,
      "ema": {
        "EMA_5": 102.37,
        "EMA_8": 102.05,
        "EMA_10": 102.13,
        "EMA_13": 102.45,
        "EMA_20": 103.44,
        "EMA_21": 103.58,
        "EMA_34": 104.77,
        "EMA_50": 104.87,
        "EMA_55": 104.73
      },
      "bb": {
        "upper": 109.99,
        "mid": 103.48,
        "lower": 96.96
      }
    },
    {
      "id": 37,
      "ticker": "GARAN.IS",
      "name": "GARAN.IS",
      "close": 140.4,
      "open": 137.7,
      "high": 140.7,
      "low": 137.3,
      "pivots": {
        "daily": 139.467,
        "monthly": 134.0,
        "monthlyP": 4.77
      },
      "rsi": 60.97,
      "ema": {
        "EMA_5": 135.15,
        "EMA_8": 132.8,
        "EMA_10": 131.87,
        "EMA_13": 131.16,
        "EMA_20": 131.24,
        "EMA_21": 131.36,
        "EMA_34": 133.28,
        "EMA_50": 135.04,
        "EMA_55": 135.4
      },
      "bb": {
        "upper": 138.94,
        "mid": 128.2,
        "lower": 117.46
      }
    },
    {
      "id": 38,
      "ticker": "GENIL.IS",
      "name": "GENIL.IS",
      "close": 10.32,
      "open": 10.36,
      "high": 10.53,
      "low": 10.2,
      "pivots": {
        "daily": 10.35,
        "monthly": 10.58,
        "monthlyP": -2.43
      },
      "rsi": 59.89,
      "ema": {
        "EMA_5": 10.42,
        "EMA_8": 10.4,
        "EMA_10": 10.36,
        "EMA_13": 10.26,
        "EMA_20": 10.02,
        "EMA_21": 9.99,
        "EMA_34": 9.72,
        "EMA_50": 9.67,
        "EMA_55": 9.69
      },
      "bb": {
        "upper": 11.22,
        "mid": 10.0,
        "lower": 8.78
      }
    },
    {
      "id": 39,
      "ticker": "GESAN.IS",
      "name": "GESAN.IS",
      "close": 50.3,
      "open": 49.62,
      "high": 50.45,
      "low": 49.4,
      "pivots": {
        "daily": 50.05,
        "monthly": 48.79,
        "monthlyP": 3.1
      },
      "rsi": 60.96,
      "ema": {
        "EMA_5": 49.03,
        "EMA_8": 48.34,
        "EMA_10": 47.99,
        "EMA_13": 47.6,
        "EMA_20": 47.22,
        "EMA_21": 47.2,
        "EMA_34": 47.41,
        "EMA_50": 47.77,
        "EMA_55": 47.84
      },
      "bb": {
        "upper": 50.1,
        "mid": 46.14,
        "lower": 42.17
      }
    },
    {
      "id": 40,
      "ticker": "GLRMK.IS",
      "name": "GLRMK.IS",
      "close": 240.5,
      "open": 242.8,
      "high": 261.0,
      "low": 238.2,
      "pivots": {
        "daily": 246.567,
        "monthly": 226.97,
        "monthlyP": 5.96
      },
      "rsi": 81.61,
      "ema": {
        "EMA_5": 223.52,
        "EMA_8": 213.18,
        "EMA_10": 208.15,
        "EMA_13": 202.38,
        "EMA_20": 193.98,
        "EMA_21": 193.16,
        "EMA_34": 186.76,
        "EMA_50": 183.67,
        "EMA_55": 183.09
      },
      "bb": {
        "upper": 231.31,
        "mid": 186.6,
        "lower": 141.89
      }
    },
    {
      "id": 41,
      "ticker": "GRSEL.IS",
      "name": "GRSEL.IS",
      "close": 318.25,
      "open": 319.5,
      "high": 321.0,
      "low": 317.25,
      "pivots": {
        "daily": 318.833,
        "monthly": 316.17,
        "monthlyP": 0.66
      },
      "rsi": 45.98,
      "ema": {
        "EMA_5": 316.26,
        "EMA_8": 315.74,
        "EMA_10": 315.97,
        "EMA_13": 317.0,
        "EMA_20": 321.05,
        "EMA_21": 321.69,
        "EMA_34": 328.92,
        "EMA_50": 334.07,
        "EMA_55": 335.02
      },
      "bb": {
        "upper": 332.83,
        "mid": 317.3,
        "lower": 301.77
      }
    },
    {
      "id": 42,
      "ticker": "GRTHO.IS",
      "name": "GRTHO.IS",
      "close": 276.0,
      "open": 251.5,
      "high": 276.0,
      "low": 251.5,
      "pivots": {
        "daily": 267.833,
        "monthly": 257.97,
        "monthlyP": 6.99
      },
      "rsi": 67.05,
      "ema": {
        "EMA_5": 254.2,
        "EMA_8": 249.11,
        "EMA_10": 247.33,
        "EMA_13": 245.78,
        "EMA_20": 244.31,
        "EMA_21": 244.21,
        "EMA_34": 244.34,
        "EMA_50": 248.25,
        "EMA_55": 250.25
      },
      "bb": {
        "upper": 264.95,
        "mid": 242.57,
        "lower": 220.19
      }
    },
    {
      "id": 43,
      "ticker": "GSRAY.IS",
      "name": "GSRAY.IS",
      "close": 1.13,
      "open": 1.13,
      "high": 1.15,
      "low": 1.12,
      "pivots": {
        "daily": 1.133,
        "monthly": 1.11,
        "monthlyP": 1.8
      },
      "rsi": 53.62,
      "ema": {
        "EMA_5": 1.1,
        "EMA_8": 1.1,
        "EMA_10": 1.09,
        "EMA_13": 1.09,
        "EMA_20": 1.1,
        "EMA_21": 1.1,
        "EMA_34": 1.12,
        "EMA_50": 1.14,
        "EMA_55": 1.15
      },
      "bb": {
        "upper": 1.17,
        "mid": 1.09,
        "lower": 1.01
      }
    },
    {
      "id": 44,
      "ticker": "GUBRF.IS",
      "name": "GUBRF.IS",
      "close": 486.5,
      "open": 492.0,
      "high": 496.25,
      "low": 482.25,
      "pivots": {
        "daily": 488.333,
        "monthly": 486.75,
        "monthlyP": -0.05
      },
      "rsi": 48.82,
      "ema": {
        "EMA_5": 485.08,
        "EMA_8": 484.07,
        "EMA_10": 484.13,
        "EMA_13": 484.96,
        "EMA_20": 487.79,
        "EMA_21": 488.12,
        "EMA_34": 488.47,
        "EMA_50": 480.65,
        "EMA_55": 477.18
      },
      "bb": {
        "upper": 520.34,
        "mid": 486.93,
        "lower": 453.51
      }
    },
    {
      "id": 45,
      "ticker": "HALKB.IS",
      "name": "HALKB.IS",
      "close": 40.0,
      "open": 39.08,
      "high": 40.04,
      "low": 39.08,
      "pivots": {
        "daily": 39.707,
        "monthly": 38.43,
        "monthlyP": 4.09
      },
      "rsi": 51.45,
      "ema": {
        "EMA_5": 38.29,
        "EMA_8": 37.89,
        "EMA_10": 37.86,
        "EMA_13": 38.03,
        "EMA_20": 38.81,
        "EMA_21": 38.93,
        "EMA_34": 40.15,
        "EMA_50": 40.71,
        "EMA_55": 40.73
      },
      "bb": {
        "upper": 41.39,
        "mid": 37.9,
        "lower": 34.41
      }
    },
    {
      "id": 46,
      "ticker": "HEKTS.IS",
      "name": "HEKTS.IS",
      "close": 3.05,
      "open": 2.96,
      "high": 3.07,
      "low": 2.95,
      "pivots": {
        "daily": 3.023,
        "monthly": 2.99,
        "monthlyP": 1.89
      },
      "rsi": 55.12,
      "ema": {
        "EMA_5": 2.97,
        "EMA_8": 2.95,
        "EMA_10": 2.94,
        "EMA_13": 2.94,
        "EMA_20": 2.95,
        "EMA_21": 2.95,
        "EMA_34": 2.98,
        "EMA_50": 3.02,
        "EMA_55": 3.03
      },
      "bb": {
        "upper": 3.06,
        "mid": 2.92,
        "lower": 2.78
      }
    },
    {
      "id": 47,
      "ticker": "ISCTR.IS",
      "name": "ISCTR.IS",
      "close": 14.71,
      "open": 14.5,
      "high": 14.76,
      "low": 14.4,
      "pivots": {
        "daily": 14.623,
        "monthly": 14.06,
        "monthlyP": 4.6
      },
      "rsi": 62.08,
      "ema": {
        "EMA_5": 14.07,
        "EMA_8": 13.8,
        "EMA_10": 13.7,
        "EMA_13": 13.62,
        "EMA_20": 13.65,
        "EMA_21": 13.66,
        "EMA_34": 13.88,
        "EMA_50": 14.04,
        "EMA_55": 14.06
      },
      "bb": {
        "upper": 14.48,
        "mid": 13.29,
        "lower": 12.11
      }
    },
    {
      "id": 48,
      "ticker": "ISMEN.IS",
      "name": "ISMEN.IS",
      "close": 43.14,
      "open": 41.3,
      "high": 43.38,
      "low": 41.3,
      "pivots": {
        "daily": 42.607,
        "monthly": 42.09,
        "monthlyP": 2.5
      },
      "rsi": 57.11,
      "ema": {
        "EMA_5": 41.68,
        "EMA_8": 41.38,
        "EMA_10": 41.29,
        "EMA_13": 41.26,
        "EMA_20": 41.41,
        "EMA_21": 41.44,
        "EMA_34": 41.74,
        "EMA_50": 41.81,
        "EMA_55": 41.79
      },
      "bb": {
        "upper": 43.2,
        "mid": 41.15,
        "lower": 39.09
      }
    },
    {
      "id": 49,
      "ticker": "IZENR.IS",
      "name": "IZENR.IS",
      "close": 9.59,
      "open": 9.55,
      "high": 9.72,
      "low": 9.46,
      "pivots": {
        "daily": 9.59,
        "monthly": 9.64,
        "monthlyP": -0.48
      },
      "rsi": 50.45,
      "ema": {
        "EMA_5": 9.52,
        "EMA_8": 9.54,
        "EMA_10": 9.55,
        "EMA_13": 9.57,
        "EMA_20": 9.57,
        "EMA_21": 9.57,
        "EMA_34": 9.56,
        "EMA_50": 9.56,
        "EMA_55": 9.56
      },
      "bb": {
        "upper": 10.24,
        "mid": 9.69,
        "lower": 9.15
      }
    },
    {
      "id": 50,
      "ticker": "KCAER.IS",
      "name": "KCAER.IS",
      "close": 11.76,
      "open": 11.6,
      "high": 11.82,
      "low": 11.57,
      "pivots": {
        "daily": 11.717,
        "monthly": 11.49,
        "monthlyP": 2.38
      },
      "rsi": 57.03,
      "ema": {
        "EMA_5": 11.47,
        "EMA_8": 11.39,
        "EMA_10": 11.36,
        "EMA_13": 11.35,
        "EMA_20": 11.34,
        "EMA_21": 11.34,
        "EMA_34": 11.33,
        "EMA_50": 11.33,
        "EMA_55": 11.33
      },
      "bb": {
        "upper": 12.16,
        "mid": 11.39,
        "lower": 10.63
      }
    },
    {
      "id": 51,
      "ticker": "KCHOL.IS",
      "name": "KCHOL.IS",
      "close": 204.0,
      "open": 200.8,
      "high": 204.6,
      "low": 200.8,
      "pivots": {
        "daily": 203.133,
        "monthly": 199.63,
        "monthlyP": 2.19
      },
      "rsi": 62.39,
      "ema": {
        "EMA_5": 199.13,
        "EMA_8": 197.21,
        "EMA_10": 196.26,
        "EMA_13": 195.18,
        "EMA_20": 193.81,
        "EMA_21": 193.69,
        "EMA_34": 192.69,
        "EMA_50": 191.29,
        "EMA_55": 190.76
      },
      "bb": {
        "upper": 202.77,
        "mid": 191.47,
        "lower": 180.16
      }
    },
    {
      "id": 52,
      "ticker": "KLRHO.IS",
      "name": "KLRHO.IS",
      "close": 106.1,
      "open": 103.9,
      "high": 108.1,
      "low": 103.1,
      "pivots": {
        "daily": 105.767,
        "monthly": 120.33,
        "monthlyP": -11.83
      },
      "rsi": 31.85,
      "ema": {
        "EMA_5": 107.65,
        "EMA_8": 111.05,
        "EMA_10": 113.92,
        "EMA_13": 119.85,
        "EMA_20": 140.53,
        "EMA_21": 143.94,
        "EMA_34": 186.87,
        "EMA_50": 222.44,
        "EMA_55": 229.55
      },
      "bb": {
        "upper": 162.0,
        "mid": 122.33,
        "lower": 82.66
      }
    },
    {
      "id": 53,
      "ticker": "KONTR.IS",
      "name": "KONTR.IS",
      "close": 9.68,
      "open": 9.68,
      "high": 9.68,
      "low": 9.48,
      "pivots": {
        "daily": 9.613,
        "monthly": 8.99,
        "monthlyP": 7.68
      },
      "rsi": 62.52,
      "ema": {
        "EMA_5": 8.73,
        "EMA_8": 8.58,
        "EMA_10": 8.56,
        "EMA_13": 8.57,
        "EMA_20": 8.66,
        "EMA_21": 8.67,
        "EMA_34": 8.99,
        "EMA_50": 9.68,
        "EMA_55": 9.95
      },
      "bb": {
        "upper": 9.71,
        "mid": 8.66,
        "lower": 7.6
      }
    },
    {
      "id": 54,
      "ticker": "KRDMD.IS",
      "name": "KRDMD.IS",
      "close": 36.1,
      "open": 36.72,
      "high": 39.24,
      "low": 35.84,
      "pivots": {
        "daily": 37.06,
        "monthly": 35.39,
        "monthlyP": 2.0
      },
      "rsi": 67.83,
      "ema": {
        "EMA_5": 34.95,
        "EMA_8": 34.05,
        "EMA_10": 33.59,
        "EMA_13": 33.07,
        "EMA_20": 32.32,
        "EMA_21": 32.24,
        "EMA_34": 31.54,
        "EMA_50": 30.95,
        "EMA_55": 30.79
      },
      "bb": {
        "upper": 36.04,
        "mid": 31.4,
        "lower": 26.76
      }
    },
    {
      "id": 55,
      "ticker": "KTLEV.IS",
      "name": "KTLEV.IS",
      "close": 80.0,
      "open": 76.5,
      "high": 81.9,
      "low": 74.45,
      "pivots": {
        "daily": 78.783,
        "monthly": 79.55,
        "monthlyP": 0.57
      },
      "rsi": 74.01,
      "ema": {
        "EMA_5": 79.12,
        "EMA_8": 78.12,
        "EMA_10": 77.11,
        "EMA_13": 75.36,
        "EMA_20": 71.08,
        "EMA_21": 70.49,
        "EMA_34": 63.66,
        "EMA_50": 57.1,
        "EMA_55": 55.36
      },
      "bb": {
        "upper": 88.46,
        "mid": 70.95,
        "lower": 53.45
      }
    },
    {
      "id": 56,
      "ticker": "KUYAS.IS",
      "name": "KUYAS.IS",
      "close": 86.15,
      "open": 85.8,
      "high": 87.5,
      "low": 84.5,
      "pivots": {
        "daily": 86.05,
        "monthly": 82.27,
        "monthlyP": 4.72
      },
      "rsi": 70.25,
      "ema": {
        "EMA_5": 83.92,
        "EMA_8": 82.32,
        "EMA_10": 81.52,
        "EMA_13": 80.53,
        "EMA_20": 78.66,
        "EMA_21": 78.41,
        "EMA_34": 75.44,
        "EMA_50": 72.26,
        "EMA_55": 71.39
      },
      "bb": {
        "upper": 86.96,
        "mid": 78.35,
        "lower": 69.74
      }
    },
    {
      "id": 57,
      "ticker": "MAGEN.IS",
      "name": "MAGEN.IS",
      "close": 61.65,
      "open": 61.05,
      "high": 62.5,
      "low": 60.65,
      "pivots": {
        "daily": 61.6,
        "monthly": 58.75,
        "monthlyP": 4.94
      },
      "rsi": 84.53,
      "ema": {
        "EMA_5": 59.2,
        "EMA_8": 57.65,
        "EMA_10": 56.82,
        "EMA_13": 55.79,
        "EMA_20": 53.97,
        "EMA_21": 53.76,
        "EMA_34": 51.48,
        "EMA_50": 49.27,
        "EMA_55": 48.64
      },
      "bb": {
        "upper": 60.97,
        "mid": 52.88,
        "lower": 44.79
      }
    },
    {
      "id": 58,
      "ticker": "MAVI.IS",
      "name": "MAVI.IS",
      "close": 43.5,
      "open": 42.84,
      "high": 43.64,
      "low": 42.68,
      "pivots": {
        "daily": 43.273,
        "monthly": 42.7,
        "monthlyP": 1.87
      },
      "rsi": 53.04,
      "ema": {
        "EMA_5": 42.69,
        "EMA_8": 42.51,
        "EMA_10": 42.46,
        "EMA_13": 42.46,
        "EMA_20": 42.63,
        "EMA_21": 42.66,
        "EMA_34": 43.1,
        "EMA_50": 43.38,
        "EMA_55": 43.42
      },
      "bb": {
        "upper": 44.41,
        "mid": 42.47,
        "lower": 40.53
      }
    },
    {
      "id": 59,
      "ticker": "MGROS.IS",
      "name": "MGROS.IS",
      "close": 656.0,
      "open": 645.5,
      "high": 656.0,
      "low": 639.0,
      "pivots": {
        "daily": 650.333,
        "monthly": 635.0,
        "monthlyP": 3.31
      },
      "rsi": 63.97,
      "ema": {
        "EMA_5": 633.08,
        "EMA_8": 625.18,
        "EMA_10": 621.82,
        "EMA_13": 618.59,
        "EMA_20": 615.96,
        "EMA_21": 615.89,
        "EMA_34": 615.95,
        "EMA_50": 613.13,
        "EMA_55": 611.5
      },
      "bb": {
        "upper": 641.46,
        "mid": 606.25,
        "lower": 571.04
      }
    },
    {
      "id": 60,
      "ticker": "MIATK.IS",
      "name": "MIATK.IS",
      "close": 43.14,
      "open": 43.08,
      "high": 43.46,
      "low": 42.6,
      "pivots": {
        "daily": 43.067,
        "monthly": 43.24,
        "monthlyP": -0.23
      },
      "rsi": 61.17,
      "ema": {
        "EMA_5": 42.55,
        "EMA_8": 42.12,
        "EMA_10": 41.84,
        "EMA_13": 41.47,
        "EMA_20": 40.8,
        "EMA_21": 40.72,
        "EMA_34": 39.97,
        "EMA_50": 39.44,
        "EMA_55": 39.33
      },
      "bb": {
        "upper": 44.44,
        "mid": 40.29,
        "lower": 36.15
      }
    },
    {
      "id": 61,
      "ticker": "MPARK.IS",
      "name": "MPARK.IS",
      "close": 443.0,
      "open": 440.75,
      "high": 448.25,
      "low": 439.75,
      "pivots": {
        "daily": 443.667,
        "monthly": 432.92,
        "monthlyP": 2.33
      },
      "rsi": 57.2,
      "ema": {
        "EMA_5": 433.07,
        "EMA_8": 429.37,
        "EMA_10": 428.23,
        "EMA_13": 427.58,
        "EMA_20": 428.2,
        "EMA_21": 428.37,
        "EMA_34": 429.8,
        "EMA_50": 427.9,
        "EMA_55": 426.71
      },
      "bb": {
        "upper": 445.64,
        "mid": 426.19,
        "lower": 406.73
      }
    },
    {
      "id": 62,
      "ticker": "OBAMS.IS",
      "name": "OBAMS.IS",
      "close": 8.32,
      "open": 8.48,
      "high": 8.49,
      "low": 8.29,
      "pivots": {
        "daily": 8.367,
        "monthly": 8.46,
        "monthlyP": -1.69
      },
      "rsi": 51.15,
      "ema": {
        "EMA_5": 8.33,
        "EMA_8": 8.34,
        "EMA_10": 8.33,
        "EMA_13": 8.32,
        "EMA_20": 8.28,
        "EMA_21": 8.28,
        "EMA_34": 8.24,
        "EMA_50": 8.21,
        "EMA_55": 8.19
      },
      "bb": {
        "upper": 8.81,
        "mid": 8.27,
        "lower": 7.74
      }
    },
    {
      "id": 63,
      "ticker": "ODAS.IS",
      "name": "ODAS.IS",
      "close": 6.73,
      "open": 6.81,
      "high": 6.95,
      "low": 6.68,
      "pivots": {
        "daily": 6.787,
        "monthly": 6.49,
        "monthlyP": 3.75
      },
      "rsi": 64.25,
      "ema": {
        "EMA_5": 6.53,
        "EMA_8": 6.4,
        "EMA_10": 6.35,
        "EMA_13": 6.28,
        "EMA_20": 6.19,
        "EMA_21": 6.18,
        "EMA_34": 6.08,
        "EMA_50": 5.98,
        "EMA_55": 5.96
      },
      "bb": {
        "upper": 6.71,
        "mid": 6.12,
        "lower": 5.52
      }
    },
    {
      "id": 64,
      "ticker": "OTKAR.IS",
      "name": "OTKAR.IS",
      "close": 394.0,
      "open": 392.0,
      "high": 396.5,
      "low": 389.25,
      "pivots": {
        "daily": 393.25,
        "monthly": 385.08,
        "monthlyP": 2.32
      },
      "rsi": 56.09,
      "ema": {
        "EMA_5": 386.98,
        "EMA_8": 383.56,
        "EMA_10": 382.1,
        "EMA_13": 380.8,
        "EMA_20": 380.67,
        "EMA_21": 380.9,
        "EMA_34": 386.86,
        "EMA_50": 396.76,
        "EMA_55": 399.81
      },
      "bb": {
        "upper": 396.72,
        "mid": 376.69,
        "lower": 356.65
      }
    },
    {
      "id": 65,
      "ticker": "OYAKC.IS",
      "name": "OYAKC.IS",
      "close": 25.6,
      "open": 25.26,
      "high": 25.64,
      "low": 25.16,
      "pivots": {
        "daily": 25.467,
        "monthly": 24.88,
        "monthlyP": 2.89
      },
      "rsi": 63.24,
      "ema": {
        "EMA_5": 24.87,
        "EMA_8": 24.56,
        "EMA_10": 24.43,
        "EMA_13": 24.29,
        "EMA_20": 24.17,
        "EMA_21": 24.16,
        "EMA_34": 24.23,
        "EMA_50": 24.31,
        "EMA_55": 24.31
      },
      "bb": {
        "upper": 25.2,
        "mid": 23.82,
        "lower": 22.44
      }
    },
    {
      "id": 66,
      "ticker": "PASEU.IS",
      "name": "PASEU.IS",
      "close": 121.0,
      "open": 117.9,
      "high": 122.2,
      "low": 117.3,
      "pivots": {
        "daily": 120.167,
        "monthly": 120.5,
        "monthlyP": 0.41
      },
      "rsi": 48.81,
      "ema": {
        "EMA_5": 118.01,
        "EMA_8": 118.16,
        "EMA_10": 118.41,
        "EMA_13": 118.85,
        "EMA_20": 120.2,
        "EMA_21": 120.42,
        "EMA_34": 123.53,
        "EMA_50": 126.73,
        "EMA_55": 127.48
      },
      "bb": {
        "upper": 124.69,
        "mid": 119.76,
        "lower": 114.82
      }
    },
    {
      "id": 67,
      "ticker": "PATEK.IS",
      "name": "PATEK.IS",
      "close": 20.02,
      "open": 18.34,
      "high": 20.02,
      "low": 18.33,
      "pivots": {
        "daily": 19.457,
        "monthly": 19.14,
        "monthlyP": 4.6
      },
      "rsi": 63.51,
      "ema": {
        "EMA_5": 18.64,
        "EMA_8": 18.4,
        "EMA_10": 18.32,
        "EMA_13": 18.25,
        "EMA_20": 18.23,
        "EMA_21": 18.24,
        "EMA_34": 18.52,
        "EMA_50": 19.09,
        "EMA_55": 19.29
      },
      "bb": {
        "upper": 19.09,
        "mid": 18.01,
        "lower": 16.92
      }
    },
    {
      "id": 68,
      "ticker": "PETKM.IS",
      "name": "PETKM.IS",
      "close": 21.36,
      "open": 21.22,
      "high": 21.96,
      "low": 21.14,
      "pivots": {
        "daily": 21.487,
        "monthly": 21.07,
        "monthlyP": 1.36
      },
      "rsi": 59.68,
      "ema": {
        "EMA_5": 21.14,
        "EMA_8": 20.92,
        "EMA_10": 20.79,
        "EMA_13": 20.61,
        "EMA_20": 20.25,
        "EMA_21": 20.21,
        "EMA_34": 19.73,
        "EMA_50": 19.31,
        "EMA_55": 19.21
      },
      "bb": {
        "upper": 21.84,
        "mid": 20.28,
        "lower": 18.72
      }
    },
    {
      "id": 69,
      "ticker": "PGSUS.IS",
      "name": "PGSUS.IS",
      "close": 188.4,
      "open": 187.0,
      "high": 188.6,
      "low": 186.5,
      "pivots": {
        "daily": 187.833,
        "monthly": 184.4,
        "monthlyP": 2.17
      },
      "rsi": 57.4,
      "ema": {
        "EMA_5": 183.94,
        "EMA_8": 182.28,
        "EMA_10": 181.66,
        "EMA_13": 181.21,
        "EMA_20": 181.58,
        "EMA_21": 181.73,
        "EMA_34": 184.4,
        "EMA_50": 187.77,
        "EMA_55": 188.75
      },
      "bb": {
        "upper": 186.3,
        "mid": 179.16,
        "lower": 172.03
      }
    },
    {
      "id": 70,
      "ticker": "QUAGR.IS",
      "name": "QUAGR.IS",
      "close": 3.55,
      "open": 3.54,
      "high": 3.6,
      "low": 3.44,
      "pivots": {
        "daily": 3.53,
        "monthly": 3.38,
        "monthlyP": 5.13
      },
      "rsi": 67.02,
      "ema": {
        "EMA_5": 3.44,
        "EMA_8": 3.36,
        "EMA_10": 3.32,
        "EMA_13": 3.27,
        "EMA_20": 3.19,
        "EMA_21": 3.18,
        "EMA_34": 3.12,
        "EMA_50": 3.14,
        "EMA_55": 3.17
      },
      "bb": {
        "upper": 3.55,
        "mid": 3.16,
        "lower": 2.77
      }
    },
    {
      "id": 71,
      "ticker": "RALYH.IS",
      "name": "RALYH.IS",
      "close": 262.75,
      "open": 242.0,
      "high": 264.0,
      "low": 241.5,
      "pivots": {
        "daily": 256.083,
        "monthly": 237.85,
        "monthlyP": 10.47
      },
      "rsi": 78.66,
      "ema": {
        "EMA_5": 235.66,
        "EMA_8": 224.66,
        "EMA_10": 218.78,
        "EMA_13": 211.35,
        "EMA_20": 199.05,
        "EMA_21": 197.76,
        "EMA_34": 187.78,
        "EMA_50": 184.09,
        "EMA_55": 183.65
      },
      "bb": {
        "upper": 262.29,
        "mid": 187.67,
        "lower": 113.05
      }
    },
    {
      "id": 72,
      "ticker": "REEDR.IS",
      "name": "REEDR.IS",
      "close": 7.52,
      "open": 7.55,
      "high": 7.64,
      "low": 7.51,
      "pivots": {
        "daily": 7.557,
        "monthly": 7.68,
        "monthlyP": -2.04
      },
      "rsi": 53.42,
      "ema": {
        "EMA_5": 7.49,
        "EMA_8": 7.49,
        "EMA_10": 7.49,
        "EMA_13": 7.46,
        "EMA_20": 7.37,
        "EMA_21": 7.36,
        "EMA_34": 7.23,
        "EMA_50": 7.19,
        "EMA_55": 7.2
      },
      "bb": {
        "upper": 8.76,
        "mid": 7.55,
        "lower": 6.34
      }
    },
    {
      "id": 73,
      "ticker": "SAHOL.IS",
      "name": "SAHOL.IS",
      "close": 102.0,
      "open": 98.0,
      "high": 102.0,
      "low": 98.0,
      "pivots": {
        "daily": 100.667,
        "monthly": 97.52,
        "monthlyP": 4.6
      },
      "rsi": 65.44,
      "ema": {
        "EMA_5": 96.57,
        "EMA_8": 94.74,
        "EMA_10": 94.03,
        "EMA_13": 93.43,
        "EMA_20": 93.15,
        "EMA_21": 93.17,
        "EMA_34": 93.68,
        "EMA_50": 93.86,
        "EMA_55": 93.8
      },
      "bb": {
        "upper": 98.82,
        "mid": 91.58,
        "lower": 84.35
      }
    },
    {
      "id": 74,
      "ticker": "SASA.IS",
      "name": "SASA.IS",
      "close": 2.62,
      "open": 2.47,
      "high": 2.64,
      "low": 2.45,
      "pivots": {
        "daily": 2.57,
        "monthly": 2.54,
        "monthlyP": 3.29
      },
      "rsi": 62.52,
      "ema": {
        "EMA_5": 2.5,
        "EMA_8": 2.47,
        "EMA_10": 2.46,
        "EMA_13": 2.45,
        "EMA_20": 2.43,
        "EMA_21": 2.43,
        "EMA_34": 2.43,
        "EMA_50": 2.46,
        "EMA_55": 2.48
      },
      "bb": {
        "upper": 2.56,
        "mid": 2.43,
        "lower": 2.29
      }
    },
    {
      "id": 75,
      "ticker": "SISE.IS",
      "name": "SISE.IS",
      "close": 47.44,
      "open": 46.82,
      "high": 47.82,
      "low": 46.7,
      "pivots": {
        "daily": 47.32,
        "monthly": 46.26,
        "monthlyP": 2.55
      },
      "rsi": 59.86,
      "ema": {
        "EMA_5": 46.17,
        "EMA_8": 45.73,
        "EMA_10": 45.55,
        "EMA_13": 45.34,
        "EMA_20": 45.03,
        "EMA_21": 44.99,
        "EMA_34": 44.62,
        "EMA_50": 44.13,
        "EMA_55": 43.96
      },
      "bb": {
        "upper": 48.52,
        "mid": 44.97,
        "lower": 41.42
      }
    },
    {
      "id": 76,
      "ticker": "SKBNK.IS",
      "name": "SKBNK.IS",
      "close": 12.14,
      "open": 12.0,
      "high": 12.18,
      "low": 11.95,
      "pivots": {
        "daily": 12.09,
        "monthly": 11.56,
        "monthlyP": 4.99
      },
      "rsi": 69.65,
      "ema": {
        "EMA_5": 11.72,
        "EMA_8": 11.46,
        "EMA_10": 11.34,
        "EMA_13": 11.22,
        "EMA_20": 11.05,
        "EMA_21": 11.03,
        "EMA_34": 10.8,
        "EMA_50": 10.5,
        "EMA_55": 10.41
      },
      "bb": {
        "upper": 12.03,
        "mid": 10.85,
        "lower": 9.68
      }
    },
    {
      "id": 77,
      "ticker": "SOKM.IS",
      "name": "SOKM.IS",
      "close": 56.35,
      "open": 55.2,
      "high": 56.5,
      "low": 54.4,
      "pivots": {
        "daily": 55.75,
        "monthly": 54.12,
        "monthlyP": 4.11
      },
      "rsi": 56.15,
      "ema": {
        "EMA_5": 54.06,
        "EMA_8": 53.27,
        "EMA_10": 53.03,
        "EMA_13": 52.98,
        "EMA_20": 53.59,
        "EMA_21": 53.71,
        "EMA_34": 55.13,
        "EMA_50": 55.89,
        "EMA_55": 55.93
      },
      "bb": {
        "upper": 56.43,
        "mid": 51.93,
        "lower": 47.44
      }
    },
    {
      "id": 78,
      "ticker": "TABGD.IS",
      "name": "TABGD.IS",
      "close": 255.0,
      "open": 252.5,
      "high": 257.5,
      "low": 250.5,
      "pivots": {
        "daily": 254.333,
        "monthly": 248.87,
        "monthlyP": 2.46
      },
      "rsi": 55.71,
      "ema": {
        "EMA_5": 247.79,
        "EMA_8": 246.55,
        "EMA_10": 246.4,
        "EMA_13": 246.61,
        "EMA_20": 247.79,
        "EMA_21": 247.96,
        "EMA_34": 249.56,
        "EMA_50": 249.66,
        "EMA_55": 249.4
      },
      "bb": {
        "upper": 259.37,
        "mid": 247.8,
        "lower": 236.24
      }
    },
    {
      "id": 79,
      "ticker": "TAVHL.IS",
      "name": "TAVHL.IS",
      "close": 345.75,
      "open": 342.25,
      "high": 349.5,
      "low": 337.25,
      "pivots": {
        "daily": 344.167,
        "monthly": 335.08,
        "monthlyP": 3.18
      },
      "rsi": 64.5,
      "ema": {
        "EMA_5": 335.62,
        "EMA_8": 329.28,
        "EMA_10": 325.96,
        "EMA_13": 322.19,
        "EMA_20": 317.53,
        "EMA_21": 317.18,
        "EMA_34": 315.53,
        "EMA_50": 314.72,
        "EMA_55": 314.26
      },
      "bb": {
        "upper": 345.93,
        "mid": 308.61,
        "lower": 271.3
      }
    },
    {
      "id": 80,
      "ticker": "TCELL.IS",
      "name": "TCELL.IS",
      "close": 117.3,
      "open": 116.1,
      "high": 117.8,
      "low": 115.4,
      "pivots": {
        "daily": 116.833,
        "monthly": 113.2,
        "monthlyP": 3.62
      },
      "rsi": 63.03,
      "ema": {
        "EMA_5": 112.58,
        "EMA_8": 111.02,
        "EMA_10": 110.44,
        "EMA_13": 109.98,
        "EMA_20": 109.84,
        "EMA_21": 109.87,
        "EMA_34": 110.28,
        "EMA_50": 110.1,
        "EMA_55": 109.92
      },
      "bb": {
        "upper": 114.43,
        "mid": 108.34,
        "lower": 102.24
      }
    },
    {
      "id": 81,
      "ticker": "THYAO.IS",
      "name": "THYAO.IS",
      "close": 323.25,
      "open": 322.5,
      "high": 325.25,
      "low": 321.0,
      "pivots": {
        "daily": 323.167,
        "monthly": 313.25,
        "monthlyP": 3.19
      },
      "rsi": 66.53,
      "ema": {
        "EMA_5": 313.12,
        "EMA_8": 308.43,
        "EMA_10": 306.34,
        "EMA_13": 304.18,
        "EMA_20": 301.79,
        "EMA_21": 301.62,
        "EMA_34": 300.72,
        "EMA_50": 300.07,
        "EMA_55": 299.84
      },
      "bb": {
        "upper": 317.26,
        "mid": 297.57,
        "lower": 277.89
      }
    },
    {
      "id": 82,
      "ticker": "TKFEN.IS",
      "name": "TKFEN.IS",
      "close": 107.6,
      "open": 110.3,
      "high": 111.8,
      "low": 107.2,
      "pivots": {
        "daily": 108.867,
        "monthly": 104.83,
        "monthlyP": 2.64
      },
      "rsi": 70.09,
      "ema": {
        "EMA_5": 103.39,
        "EMA_8": 101.28,
        "EMA_10": 100.02,
        "EMA_13": 98.28,
        "EMA_20": 94.91,
        "EMA_21": 94.5,
        "EMA_34": 90.34,
        "EMA_50": 87.16,
        "EMA_55": 86.45
      },
      "bb": {
        "upper": 110.14,
        "mid": 93.38,
        "lower": 76.62
      }
    },
    {
      "id": 83,
      "ticker": "TOASO.IS",
      "name": "TOASO.IS",
      "close": 284.75,
      "open": 278.5,
      "high": 286.0,
      "low": 278.0,
      "pivots": {
        "daily": 282.917,
        "monthly": 274.25,
        "monthlyP": 3.83
      },
      "rsi": 54.12,
      "ema": {
        "EMA_5": 274.73,
        "EMA_8": 273.26,
        "EMA_10": 273.27,
        "EMA_13": 273.88,
        "EMA_20": 276.06,
        "EMA_21": 276.37,
        "EMA_34": 278.86,
        "EMA_50": 278.44,
        "EMA_55": 277.82
      },
      "bb": {
        "upper": 297.55,
        "mid": 277.17,
        "lower": 256.78
      }
    },
    {
      "id": 84,
      "ticker": "TRALT.IS",
      "name": "TRALT.IS",
      "close": 44.64,
      "open": 44.06,
      "high": 44.96,
      "low": 43.4,
      "pivots": {
        "daily": 44.333,
        "monthly": 43.75,
        "monthlyP": 2.03
      },
      "rsi": 45.21,
      "ema": {
        "EMA_5": 43.8,
        "EMA_8": 43.76,
        "EMA_10": 43.9,
        "EMA_13": 44.28,
        "EMA_20": 45.41,
        "EMA_21": 45.56,
        "EMA_34": 47.02,
        "EMA_50": 47.57,
        "EMA_55": 47.57
      },
      "bb": {
        "upper": 52.21,
        "mid": 45.07,
        "lower": 37.92
      }
    },
    {
      "id": 85,
      "ticker": "TRENJ.IS",
      "name": "TRENJ.IS",
      "close": 95.85,
      "open": 95.3,
      "high": 96.8,
      "low": 94.25,
      "pivots": {
        "daily": 95.633,
        "monthly": 94.07,
        "monthlyP": 1.9
      },
      "rsi": 45.95,
      "ema": {
        "EMA_5": 94.1,
        "EMA_8": 93.9,
        "EMA_10": 94.1,
        "EMA_13": 94.68,
        "EMA_20": 96.45,
        "EMA_21": 96.7,
        "EMA_34": 99.08,
        "EMA_50": 100.0,
        "EMA_55": 99.99
      },
      "bb": {
        "upper": 106.14,
        "mid": 95.82,
        "lower": 85.49
      }
    },
    {
      "id": 86,
      "ticker": "TRMET.IS",
      "name": "TRMET.IS",
      "close": 135.0,
      "open": 130.4,
      "high": 135.0,
      "low": 128.4,
      "pivots": {
        "daily": 132.8,
        "monthly": 129.13,
        "monthlyP": 4.54
      },
      "rsi": 52.01,
      "ema": {
        "EMA_5": 129.78,
        "EMA_8": 128.56,
        "EMA_10": 128.52,
        "EMA_13": 129.09,
        "EMA_20": 131.3,
        "EMA_21": 131.6,
        "EMA_34": 134.05,
        "EMA_50": 133.96,
        "EMA_55": 133.55
      },
      "bb": {
        "upper": 149.39,
        "mid": 130.51,
        "lower": 111.63
      }
    },
    {
      "id": 87,
      "ticker": "TSKB.IS",
      "name": "TSKB.IS",
      "close": 12.29,
      "open": 12.08,
      "high": 12.32,
      "low": 12.08,
      "pivots": {
        "daily": 12.23,
        "monthly": 11.92,
        "monthlyP": 3.1
      },
      "rsi": 61.56,
      "ema": {
        "EMA_5": 11.91,
        "EMA_8": 11.77,
        "EMA_10": 11.72,
        "EMA_13": 11.68,
        "EMA_20": 11.67,
        "EMA_21": 11.68,
        "EMA_34": 11.79,
        "EMA_50": 11.92,
        "EMA_55": 11.95
      },
      "bb": {
        "upper": 12.26,
        "mid": 11.57,
        "lower": 10.89
      }
    },
    {
      "id": 88,
      "ticker": "TSPOR.IS",
      "name": "TSPOR.IS",
      "close": 0.98,
      "open": 0.99,
      "high": 1.0,
      "low": 0.96,
      "pivots": {
        "daily": 0.98,
        "monthly": 0.97,
        "monthlyP": 1.38
      },
      "rsi": 53.67,
      "ema": {
        "EMA_5": 0.97,
        "EMA_8": 0.96,
        "EMA_10": 0.96,
        "EMA_13": 0.96,
        "EMA_20": 0.96,
        "EMA_21": 0.96,
        "EMA_34": 0.97,
        "EMA_50": 1.0,
        "EMA_55": 1.0
      },
      "bb": {
        "upper": 0.99,
        "mid": 0.95,
        "lower": 0.91
      }
    },
    {
      "id": 89,
      "ticker": "TTKOM.IS",
      "name": "TTKOM.IS",
      "close": 63.55,
      "open": 62.35,
      "high": 63.8,
      "low": 62.15,
      "pivots": {
        "daily": 63.167,
        "monthly": 61.52,
        "monthlyP": 3.31
      },
      "rsi": 59.08,
      "ema": {
        "EMA_5": 61.21,
        "EMA_8": 60.49,
        "EMA_10": 60.25,
        "EMA_13": 60.12,
        "EMA_20": 60.35,
        "EMA_21": 60.41,
        "EMA_34": 61.15,
        "EMA_50": 61.54,
        "EMA_55": 61.55
      },
      "bb": {
        "upper": 62.47,
        "mid": 59.38,
        "lower": 56.3
      }
    },
    {
      "id": 90,
      "ticker": "TTRAK.IS",
      "name": "TTRAK.IS",
      "close": 478.0,
      "open": 463.75,
      "high": 480.25,
      "low": 462.0,
      "pivots": {
        "daily": 473.417,
        "monthly": 464.17,
        "monthlyP": 2.98
      },
      "rsi": 57.73,
      "ema": {
        "EMA_5": 462.63,
        "EMA_8": 458.66,
        "EMA_10": 457.47,
        "EMA_13": 457.08,
        "EMA_20": 460.35,
        "EMA_21": 461.11,
        "EMA_34": 472.93,
        "EMA_50": 486.15,
        "EMA_55": 489.64
      },
      "bb": {
        "upper": 470.1,
        "mid": 454.06,
        "lower": 438.02
      }
    },
    {
      "id": 91,
      "ticker": "TUKAS.IS",
      "name": "TUKAS.IS",
      "close": 2.43,
      "open": 2.39,
      "high": 2.43,
      "low": 2.39,
      "pivots": {
        "daily": 2.417,
        "monthly": 2.38,
        "monthlyP": 1.96
      },
      "rsi": 54.32,
      "ema": {
        "EMA_5": 2.39,
        "EMA_8": 2.37,
        "EMA_10": 2.36,
        "EMA_13": 2.36,
        "EMA_20": 2.37,
        "EMA_21": 2.37,
        "EMA_34": 2.42,
        "EMA_50": 2.47,
        "EMA_55": 2.48
      },
      "bb": {
        "upper": 2.42,
        "mid": 2.33,
        "lower": 2.25
      }
    },
    {
      "id": 92,
      "ticker": "TUPRS.IS",
      "name": "TUPRS.IS",
      "close": 254.5,
      "open": 253.5,
      "high": 256.25,
      "low": 251.75,
      "pivots": {
        "daily": 254.167,
        "monthly": 253.07,
        "monthlyP": 0.57
      },
      "rsi": 56.77,
      "ema": {
        "EMA_5": 254.67,
        "EMA_8": 254.31,
        "EMA_10": 253.87,
        "EMA_13": 252.97,
        "EMA_20": 250.09,
        "EMA_21": 249.63,
        "EMA_34": 243.47,
        "EMA_50": 236.42,
        "EMA_55": 234.4
      },
      "bb": {
        "upper": 263.25,
        "mid": 253.0,
        "lower": 242.75
      }
    },
    {
      "id": 93,
      "ticker": "TUREX.IS",
      "name": "TUREX.IS",
      "close": 8.03,
      "open": 7.95,
      "high": 8.1,
      "low": 7.92,
      "pivots": {
        "daily": 8.017,
        "monthly": 7.89,
        "monthlyP": 1.82
      },
      "rsi": 58.29,
      "ema": {
        "EMA_5": 7.9,
        "EMA_8": 7.83,
        "EMA_10": 7.78,
        "EMA_13": 7.73,
        "EMA_20": 7.64,
        "EMA_21": 7.63,
        "EMA_34": 7.56,
        "EMA_50": 7.54,
        "EMA_55": 7.55
      },
      "bb": {
        "upper": 8.34,
        "mid": 7.63,
        "lower": 6.93
      }
    },
    {
      "id": 94,
      "ticker": "TURSG.IS",
      "name": "TURSG.IS",
      "close": 13.42,
      "open": 13.53,
      "high": 13.8,
      "low": 13.29,
      "pivots": {
        "daily": 13.503,
        "monthly": 13.21,
        "monthlyP": 1.62
      },
      "rsi": 60.88,
      "ema": {
        "EMA_5": 13.1,
        "EMA_8": 12.99,
        "EMA_10": 12.96,
        "EMA_13": 12.92,
        "EMA_20": 12.86,
        "EMA_21": 12.85,
        "EMA_34": 12.74,
        "EMA_50": 12.61,
        "EMA_55": 12.57
      },
      "bb": {
        "upper": 13.85,
        "mid": 13.0,
        "lower": 12.15
      }
    },
    {
      "id": 95,
      "ticker": "ULKER.IS",
      "name": "ULKER.IS",
      "close": 120.1,
      "open": 118.3,
      "high": 120.1,
      "low": 117.7,
      "pivots": {
        "daily": 119.3,
        "monthly": 117.77,
        "monthlyP": 1.98
      },
      "rsi": 55.72,
      "ema": {
        "EMA_5": 118.04,
        "EMA_8": 117.33,
        "EMA_10": 116.95,
        "EMA_13": 116.6,
        "EMA_20": 116.61,
        "EMA_21": 116.67,
        "EMA_34": 117.82,
        "EMA_50": 118.76,
        "EMA_55": 118.9
      },
      "bb": {
        "upper": 121.08,
        "mid": 114.16,
        "lower": 107.24
      }
    },
    {
      "id": 96,
      "ticker": "VAKBN.IS",
      "name": "VAKBN.IS",
      "close": 34.94,
      "open": 34.06,
      "high": 34.94,
      "low": 33.94,
      "pivots": {
        "daily": 34.607,
        "monthly": 33.38,
        "monthlyP": 4.67
      },
      "rsi": 58.06,
      "ema": {
        "EMA_5": 33.36,
        "EMA_8": 32.83,
        "EMA_10": 32.66,
        "EMA_13": 32.61,
        "EMA_20": 32.89,
        "EMA_21": 32.95,
        "EMA_34": 33.59,
        "EMA_50": 33.85,
        "EMA_55": 33.83
      },
      "bb": {
        "upper": 34.5,
        "mid": 32.04,
        "lower": 29.59
      }
    },
    {
      "id": 97,
      "ticker": "VESTL.IS",
      "name": "VESTL.IS",
      "close": 28.28,
      "open": 27.78,
      "high": 28.48,
      "low": 27.62,
      "pivots": {
        "daily": 28.127,
        "monthly": 28.78,
        "monthlyP": -1.74
      },
      "rsi": 46.72,
      "ema": {
        "EMA_5": 28.19,
        "EMA_8": 28.28,
        "EMA_10": 28.33,
        "EMA_13": 28.4,
        "EMA_20": 28.57,
        "EMA_21": 28.59,
        "EMA_34": 28.92,
        "EMA_50": 29.31,
        "EMA_55": 29.42
      },
      "bb": {
        "upper": 29.57,
        "mid": 28.56,
        "lower": 27.54
      }
    },
    {
      "id": 98,
      "ticker": "YEOTK.IS",
      "name": "YEOTK.IS",
      "close": 52.3,
      "open": 51.45,
      "high": 52.3,
      "low": 50.75,
      "pivots": {
        "daily": 51.783,
        "monthly": 52.21,
        "monthlyP": 0.17
      },
      "rsi": 58.2,
      "ema": {
        "EMA_5": 51.44,
        "EMA_8": 51.38,
        "EMA_10": 51.28,
        "EMA_13": 51.01,
        "EMA_20": 50.1,
        "EMA_21": 49.96,
        "EMA_34": 48.23,
        "EMA_50": 46.56,
        "EMA_55": 46.12
      },
      "bb": {
        "upper": 54.19,
        "mid": 51.16,
        "lower": 48.13
      }
    },
    {
      "id": 99,
      "ticker": "YKBNK.IS",
      "name": "YKBNK.IS",
      "close": 38.66,
      "open": 38.0,
      "high": 38.82,
      "low": 38.0,
      "pivots": {
        "daily": 38.493,
        "monthly": 36.97,
        "monthlyP": 4.56
      },
      "rsi": 61.71,
      "ema": {
        "EMA_5": 37.01,
        "EMA_8": 36.29,
        "EMA_10": 36.01,
        "EMA_13": 35.79,
        "EMA_20": 35.78,
        "EMA_21": 35.81,
        "EMA_34": 36.27,
        "EMA_50": 36.63,
        "EMA_55": 36.68
      },
      "bb": {
        "upper": 37.96,
        "mid": 34.84,
        "lower": 31.73
      }
    },
    {
      "id": 100,
      "ticker": "ZOREN.IS",
      "name": "ZOREN.IS",
      "close": 2.92,
      "open": 2.86,
      "high": 2.93,
      "low": 2.85,
      "pivots": {
        "daily": 2.9,
        "monthly": 2.88,
        "monthlyP": 1.39
      },
      "rsi": 49.07,
      "ema": {
        "EMA_5": 2.87,
        "EMA_8": 2.86,
        "EMA_10": 2.86,
        "EMA_13": 2.87,
        "EMA_20": 2.89,
        "EMA_21": 2.9,
        "EMA_34": 2.97,
        "EMA_50": 3.03,
        "EMA_55": 3.04
      },
      "bb": {
        "upper": 2.97,
        "mid": 2.86,
        "lower": 2.74
      }
    }
  ]
}