{
  "updated_at": "2026-07-16T05:13:11.734226Z",
  "indexes": [
    {
      "id": 4,
      "ticker": "UKOIL",
      "name": "Brent Petrol",
      "tier": {
        "no": 4,
        "amount": 10000
      },
      "close": 84.95,
      "open": 85.21,
      "high": 86.53,
      "low": 83.34,
      "volume_analysis": {
        "volume_ratio": 2.1,
        "is_volume_burst": true
      },
      "divergence": {
        "status": "NONE",
        "rsi_divergence": false,
        "volume_divergence": false
      },
      "rsi": 54.88,
      "pivots": {
        "daily": 84.94,
        "dailyP": 0.01,
        "weekly": 75.87,
        "weeklyP": 11.97,
        "monthly": 81.11,
        "monthlyP": 4.73,
        "daily_levels": {
          "r1": 86.54,
          "r2": 88.13,
          "r3": 89.73,
          "s1": 83.35,
          "s2": 81.75,
          "s3": 80.16
        },
        "weekly_levels": {
          "r1": 80.71,
          "r2": 85.41,
          "r3": 90.25,
          "s1": 71.17,
          "s2": 66.33,
          "s3": 61.63
        },
        "monthly_levels": {
          "r1": 90.81,
          "r2": 108.71,
          "r3": 118.41,
          "s1": 63.21,
          "s2": 53.51,
          "s3": 35.61
        }
      },
      "ema": {
        "EMA_100": 87.36,
        "EMA_200": 82.96
      },
      "bb": {
        "upper": 85.65,
        "mid": 77.23,
        "lower": 68.81
      }
    },
    {
      "id": 6,
      "ticker": "XAUUSD",
      "name": "Ons Altın",
      "tier": {
        "no": 4,
        "amount": 10000
      },
      "close": 4044.0,
      "open": 4049.1,
      "high": 4070.1,
      "low": 4019.4,
      "volume_analysis": {
        "volume_ratio": 2.19,
        "is_volume_burst": true
      },
      "divergence": {
        "status": "NONE",
        "rsi_divergence": false,
        "volume_divergence": false
      },
      "rsi": 40.97,
      "pivots": {
        "daily": 4044.5,
        "dailyP": -0.01,
        "weekly": 4118.93,
        "weeklyP": -1.82,
        "monthly": 4175.6,
        "monthlyP": -3.15,
        "daily_levels": {
          "r1": 4069.6,
          "r2": 4095.2,
          "r3": 4120.3,
          "s1": 4018.9,
          "s2": 3993.8,
          "s3": 3968.2
        },
        "weekly_levels": {
          "r1": 4184.87,
          "r2": 4265.63,
          "r3": 4331.57,
          "s1": 4038.17,
          "s2": 3972.23,
          "s3": 3891.47
        },
        "monthly_levels": {
          "r1": 4388.7,
          "r2": 4754.5,
          "r3": 4967.6,
          "s1": 3809.8,
          "s2": 3596.7,
          "s3": 3230.9
        }
      },
      "ema": {
        "EMA_100": 4412.17,
        "EMA_200": 4306.89
      },
      "bb": {
        "upper": 4309.24,
        "mid": 4112.98,
        "lower": 3916.71
      }
    },
    {
      "id": 14,
      "ticker": "XBANK",
      "name": "XBANK",
      "tier": {
        "no": 0,
        "amount": 0
      },
      "close": 16422.2,
      "open": 16179.8,
      "high": 16486.6,
      "low": 16131.5,
      "volume_analysis": {
        "volume_ratio": 1.06,
        "is_volume_burst": false
      },
      "divergence": {
        "status": "NONE",
        "rsi_divergence": false,
        "volume_divergence": false
      },
      "rsi": 38.25,
      "pivots": {
        "daily": 16346.77,
        "dailyP": 0.46,
        "weekly": 16894.17,
        "weeklyP": -2.79,
        "monthly": 17545.83,
        "monthlyP": -6.4,
        "daily_levels": {
          "r1": 16562.04,
          "r2": 16701.87,
          "r3": 16917.14,
          "s1": 16206.94,
          "s2": 15991.67,
          "s3": 15851.84
        },
        "weekly_levels": {
          "r1": 17339.53,
          "r2": 18169.07,
          "r3": 18614.43,
          "s1": 16064.63,
          "s2": 15619.27,
          "s3": 14789.73
        },
        "monthly_levels": {
          "r1": 19627.07,
          "r2": 21287.33,
          "r3": 23368.57,
          "s1": 15885.57,
          "s2": 13804.33,
          "s3": 12144.07
        }
      },
      "ema": {
        "EMA_100": 17196.36,
        "EMA_200": 16771.36
      },
      "bb": {
        "upper": 19548.8,
        "mid": 17799.72,
        "lower": 16050.63
      }
    },
    {
      "id": 15,
      "ticker": "XU030",
      "name": "Bist 30",
      "tier": {
        "no": 0,
        "amount": 0
      },
      "close": 16174.8,
      "open": 16093.0,
      "high": 16221.9,
      "low": 16030.4,
      "volume_analysis": {
        "volume_ratio": 1.02,
        "is_volume_burst": false
      },
      "divergence": {
        "status": "NONE",
        "rsi_divergence": false,
        "volume_divergence": false
      },
      "rsi": 44.34,
      "pivots": {
        "daily": 16142.37,
        "dailyP": 0.2,
        "weekly": 16658.57,
        "weeklyP": -2.9,
        "monthly": 16322.57,
        "monthlyP": -0.91,
        "daily_levels": {
          "r1": 16254.34,
          "r2": 16333.87,
          "r3": 16445.84,
          "s1": 16062.84,
          "s2": 15950.87,
          "s3": 15871.34
        },
        "weekly_levels": {
          "r1": 17033.13,
          "r2": 17451.07,
          "r3": 17825.63,
          "s1": 16240.63,
          "s2": 15866.07,
          "s3": 15448.13
        },
        "monthly_levels": {
          "r1": 17230.13,
          "r2": 18120.77,
          "r3": 19028.33,
          "s1": 15431.93,
          "s2": 14524.37,
          "s3": 13633.73
        }
      },
      "ema": {
        "EMA_100": 15729.66,
        "EMA_200": 14652.3
      },
      "bb": {
        "upper": 17147.71,
        "mid": 16639.81,
        "lower": 16131.92
      }
    },
    {
      "id": 16,
      "ticker": "XU030D1!",
      "name": "BIST 30 Yakın Vade Kontratı",
      "tier": {
        "no": 0,
        "amount": 0
      },
      "close": 0.0,
      "open": 0.0,
      "high": 0.0,
      "low": 0.0,
      "volume_analysis": {
        "volume_ratio": 0.0,
        "is_volume_burst": false
      },
      "divergence": {
        "status": "NONE",
        "rsi_divergence": false,
        "volume_divergence": false
      },
      "rsi": 0.0,
      "pivots": {
        "daily": 0.0,
        "dailyP": 0.0,
        "weekly": 0.0,
        "weeklyP": 0.0,
        "monthly": 0.0,
        "monthlyP": 0.0
      },
      "ema": {
        "EMA_100": 0.0,
        "EMA_200": 0.0
      },
      "bb": {
        "upper": 0.0,
        "mid": 0.0,
        "lower": 0.0
      }
    },
    {
      "id": 17,
      "ticker": "XU100",
      "name": "Bist 100",
      "tier": {
        "no": 0,
        "amount": 0
      },
      "close": 14080.0,
      "open": 13988.4,
      "high": 14115.6,
      "low": 13942.0,
      "volume_analysis": {
        "volume_ratio": 0.98,
        "is_volume_burst": false
      },
      "divergence": {
        "status": "NONE",
        "rsi_divergence": false,
        "volume_divergence": false
      },
      "rsi": 45.34,
      "pivots": {
        "daily": 14045.87,
        "dailyP": 0.24,
        "weekly": 14334.8,
        "weeklyP": -1.78,
        "monthly": 14188.43,
        "monthlyP": -0.76,
        "daily_levels": {
          "r1": 14149.74,
          "r2": 14219.47,
          "r3": 14323.34,
          "s1": 13976.14,
          "s2": 13872.27,
          "s3": 13802.54
        },
        "weekly_levels": {
          "r1": 14616.1,
          "r2": 14911.0,
          "r3": 15192.3,
          "s1": 14039.9,
          "s2": 13758.6,
          "s3": 13463.7
        },
        "monthly_levels": {
          "r1": 14809.47,
          "r2": 15497.13,
          "r3": 16118.17,
          "s1": 13500.77,
          "s2": 12879.73,
          "s3": 12192.07
        }
      },
      "ema": {
        "EMA_100": 13789.94,
        "EMA_200": 12979.25
      },
      "bb": {
        "upper": 14796.16,
        "mid": 14367.82,
        "lower": 13939.48
      }
    }
  ],
  "stocks": [
    {
      "id": 1,
      "ticker": "AKBNK",
      "name": "Akbank T.A.Ş.",
      "tier": {
        "no": 1,
        "amount": 200000
      },
      "close": 69.1,
      "open": 67.6,
      "high": 69.55,
      "low": 67.45,
      "volume_analysis": {
        "volume_ratio": 0.9,
        "is_volume_burst": false
      },
      "divergence": {
        "status": "NONE",
        "rsi_divergence": false,
        "volume_divergence": false
      },
      "rsi": 38.71,
      "pivots": {
        "daily": 68.7,
        "dailyP": 0.58,
        "weekly": 70.83,
        "weeklyP": -2.44,
        "monthly": 74.47,
        "monthlyP": -7.21,
        "daily_levels": {
          "r1": 69.95,
          "r2": 70.8,
          "r3": 72.05,
          "s1": 67.85,
          "s2": 66.6,
          "s3": 65.75
        },
        "weekly_levels": {
          "r1": 73.07,
          "r2": 77.38,
          "r3": 79.62,
          "s1": 66.52,
          "s2": 64.28,
          "s3": 59.97
        },
        "monthly_levels": {
          "r1": 85.53,
          "r2": 94.07,
          "r3": 105.13,
          "s1": 65.93,
          "s2": 54.87,
          "s3": 46.33
        }
      },
      "ema": {
        "EMA_100": 73.52,
        "EMA_200": 71.8
      },
      "bb": {
        "upper": 84.81,
        "mid": 75.8,
        "lower": 66.79
      }
    },
    {
      "id": 2,
      "ticker": "ASELS",
      "name": "Aselsan Elektronik Sanayi ve Ticaret A.Ş.",
      "tier": {
        "no": 1,
        "amount": 200000
      },
      "close": 348.5,
      "open": 352.75,
      "high": 353.25,
      "low": 345.5,
      "volume_analysis": {
        "volume_ratio": 0.79,
        "is_volume_burst": false
      },
      "divergence": {
        "status": "NONE",
        "rsi_divergence": false,
        "volume_divergence": false
      },
      "rsi": 40.74,
      "pivots": {
        "daily": 349.08,
        "dailyP": -0.17,
        "weekly": 378.75,
        "weeklyP": -7.99,
        "monthly": 366.75,
        "monthlyP": -4.98,
        "daily_levels": {
          "r1": 352.66,
          "r2": 356.83,
          "r3": 360.41,
          "s1": 344.91,
          "s2": 341.33,
          "s3": 337.16
        },
        "weekly_levels": {
          "r1": 402.5,
          "r2": 435.0,
          "r3": 458.75,
          "s1": 346.25,
          "s2": 322.5,
          "s3": 290.0
        },
        "monthly_levels": {
          "r1": 391.0,
          "r2": 437.0,
          "r3": 461.25,
          "s1": 320.75,
          "s2": 296.5,
          "s3": 250.5
        }
      },
      "ema": {
        "EMA_100": 359.24,
        "EMA_200": 311.44
      },
      "bb": {
        "upper": 415.93,
        "mid": 377.35,
        "lower": 338.77
      }
    },
    {
      "id": 3,
      "ticker": "ASTOR",
      "name": "Astor Enerji A.Ş.",
      "tier": {
        "no": 2,
        "amount": 100000
      },
      "close": 325.0,
      "open": 317.5,
      "high": 330.75,
      "low": 314.0,
      "volume_analysis": {
        "volume_ratio": 1.09,
        "is_volume_burst": false
      },
      "divergence": {
        "status": "NONE",
        "rsi_divergence": false,
        "volume_divergence": false
      },
      "rsi": 56.66,
      "pivots": {
        "daily": 323.25,
        "dailyP": 0.54,
        "weekly": 321.67,
        "weeklyP": 1.04,
        "monthly": 308.25,
        "monthlyP": 5.43,
        "daily_levels": {
          "r1": 332.5,
          "r2": 340.0,
          "r3": 349.25,
          "s1": 315.75,
          "s2": 306.5,
          "s3": 299.0
        },
        "weekly_levels": {
          "r1": 340.58,
          "r2": 355.42,
          "r3": 374.33,
          "s1": 306.83,
          "s2": 287.92,
          "s3": 273.08
        },
        "monthly_levels": {
          "r1": 354.0,
          "r2": 431.5,
          "r3": 477.25,
          "s1": 230.75,
          "s2": 185.0,
          "s3": 107.5
        }
      },
      "ema": {
        "EMA_100": 258.99,
        "EMA_200": 211.52
      },
      "bb": {
        "upper": 335.14,
        "mid": 302.94,
        "lower": 270.74
      }
    },
    {
      "id": 5,
      "ticker": "GARAN",
      "name": "Türkiye Garanti Bankası A.Ş.",
      "tier": {
        "no": 1,
        "amount": 200000
      },
      "close": 128.9,
      "open": 125.8,
      "high": 129.2,
      "low": 125.7,
      "volume_analysis": {
        "volume_ratio": 0.82,
        "is_volume_burst": false
      },
      "divergence": {
        "status": "NONE",
        "rsi_divergence": false,
        "volume_divergence": false
      },
      "rsi": 40.17,
      "pivots": {
        "daily": 127.93,
        "dailyP": 0.76,
        "weekly": 130.97,
        "weeklyP": -1.58,
        "monthly": 135.07,
        "monthlyP": -4.57,
        "daily_levels": {
          "r1": 130.16,
          "r2": 131.43,
          "r3": 133.66,
          "s1": 126.66,
          "s2": 124.43,
          "s3": 123.16
        },
        "weekly_levels": {
          "r1": 134.53,
          "r2": 140.07,
          "r3": 143.63,
          "s1": 125.43,
          "s2": 121.87,
          "s3": 116.33
        },
        "monthly_levels": {
          "r1": 148.03,
          "r2": 158.07,
          "r3": 171.03,
          "s1": 125.03,
          "s2": 112.07,
          "s3": 102.03
        }
      },
      "ema": {
        "EMA_100": 136.1,
        "EMA_200": 136.23
      },
      "bb": {
        "upper": 146.81,
        "mid": 136.43,
        "lower": 126.05
      }
    },
    {
      "id": 7,
      "ticker": "ISCTR",
      "name": "Türkiye İş Bankası A.Ş.",
      "tier": {
        "no": 1,
        "amount": 200000
      },
      "close": 13.89,
      "open": 13.69,
      "high": 13.97,
      "low": 13.63,
      "volume_analysis": {
        "volume_ratio": 0.96,
        "is_volume_burst": false
      },
      "divergence": {
        "status": "NONE",
        "rsi_divergence": false,
        "volume_divergence": false
      },
      "rsi": 42.5,
      "pivots": {
        "daily": 13.83,
        "dailyP": 0.43,
        "weekly": 14.06,
        "weeklyP": -1.21,
        "monthly": 14.46,
        "monthlyP": -3.94,
        "daily_levels": {
          "r1": 14.03,
          "r2": 14.17,
          "r3": 14.37,
          "s1": 13.69,
          "s2": 13.49,
          "s3": 13.35
        },
        "weekly_levels": {
          "r1": 14.43,
          "r2": 15.07,
          "r3": 15.44,
          "s1": 13.42,
          "s2": 13.05,
          "s3": 12.41
        },
        "monthly_levels": {
          "r1": 15.89,
          "r2": 16.97,
          "r3": 18.4,
          "s1": 13.38,
          "s2": 11.95,
          "s3": 10.87
        }
      },
      "ema": {
        "EMA_100": 14.35,
        "EMA_200": 14.22
      },
      "bb": {
        "upper": 15.71,
        "mid": 14.62,
        "lower": 13.53
      }
    },
    {
      "id": 8,
      "ticker": "KCHOL",
      "name": "Koç Holding A.Ş.",
      "tier": {
        "no": 1,
        "amount": 200000
      },
      "close": 191.1,
      "open": 191.0,
      "high": 191.9,
      "low": 189.1,
      "volume_analysis": {
        "volume_ratio": 0.95,
        "is_volume_burst": false
      },
      "divergence": {
        "status": "VOLUME",
        "rsi_divergence": false,
        "volume_divergence": true
      },
      "rsi": 48.6,
      "pivots": {
        "daily": 190.7,
        "dailyP": 0.21,
        "weekly": 189.53,
        "weeklyP": 0.83,
        "monthly": 192.0,
        "monthlyP": -0.47,
        "daily_levels": {
          "r1": 192.3,
          "r2": 193.5,
          "r3": 195.1,
          "s1": 189.5,
          "s2": 187.9,
          "s3": 186.7
        },
        "weekly_levels": {
          "r1": 196.97,
          "r2": 201.13,
          "r3": 208.57,
          "s1": 185.37,
          "s2": 177.93,
          "s3": 173.77
        },
        "monthly_levels": {
          "r1": 203.8,
          "r2": 214.1,
          "r3": 225.9,
          "s1": 181.7,
          "s2": 169.9,
          "s3": 159.6
        }
      },
      "ema": {
        "EMA_100": 193.8,
        "EMA_200": 189.33
      },
      "bb": {
        "upper": 200.72,
        "mid": 192.74,
        "lower": 184.76
      }
    },
    {
      "id": 9,
      "ticker": "PETKM",
      "name": "Petkim Petrokimya Holding A.Ş.",
      "tier": {
        "no": 2,
        "amount": 100000
      },
      "close": 19.6,
      "open": 20.04,
      "high": 20.1,
      "low": 19.59,
      "volume_analysis": {
        "volume_ratio": 1.01,
        "is_volume_burst": false
      },
      "divergence": {
        "status": "NONE",
        "rsi_divergence": false,
        "volume_divergence": false
      },
      "rsi": 45.79,
      "pivots": {
        "daily": 19.76,
        "dailyP": -0.81,
        "weekly": 19.28,
        "weeklyP": 1.66,
        "monthly": 20.78,
        "monthlyP": -5.68,
        "daily_levels": {
          "r1": 19.93,
          "r2": 20.27,
          "r3": 20.44,
          "s1": 19.42,
          "s2": 19.25,
          "s3": 18.91
        },
        "weekly_levels": {
          "r1": 19.77,
          "r2": 20.21,
          "r3": 20.7,
          "s1": 18.84,
          "s2": 18.35,
          "s3": 17.91
        },
        "monthly_levels": {
          "r1": 22.75,
          "r2": 26.38,
          "r3": 28.35,
          "s1": 17.15,
          "s2": 15.18,
          "s3": 11.55
        }
      },
      "ema": {
        "EMA_100": 20.45,
        "EMA_200": 19.75
      },
      "bb": {
        "upper": 20.45,
        "mid": 19.47,
        "lower": 18.5
      }
    },
    {
      "id": 10,
      "ticker": "SAHOL",
      "name": "Hacı Ömer Sabancı Holding A.Ş.",
      "tier": {
        "no": 1,
        "amount": 200000
      },
      "close": 89.45,
      "open": 89.1,
      "high": 90.05,
      "low": 88.65,
      "volume_analysis": {
        "volume_ratio": 1.03,
        "is_volume_burst": false
      },
      "divergence": {
        "status": "RSI",
        "rsi_divergence": true,
        "volume_divergence": false
      },
      "rsi": 36.65,
      "pivots": {
        "daily": 89.38,
        "dailyP": 0.08,
        "weekly": 92.07,
        "weeklyP": -2.85,
        "monthly": 96.53,
        "monthlyP": -7.33,
        "daily_levels": {
          "r1": 90.11,
          "r2": 90.78,
          "r3": 91.51,
          "s1": 88.71,
          "s2": 87.98,
          "s3": 87.31
        },
        "weekly_levels": {
          "r1": 95.38,
          "r2": 100.27,
          "r3": 103.58,
          "s1": 87.18,
          "s2": 83.87,
          "s3": 78.98
        },
        "monthly_levels": {
          "r1": 104.27,
          "r2": 111.03,
          "r3": 118.77,
          "s1": 89.77,
          "s2": 82.03,
          "s3": 75.27
        }
      },
      "ema": {
        "EMA_100": 94.8,
        "EMA_200": 93.38
      },
      "bb": {
        "upper": 104.48,
        "mid": 95.89,
        "lower": 87.3
      }
    },
    {
      "id": 11,
      "ticker": "TCELL",
      "name": "Turkcell İletişim Hizmetleri A.Ş.",
      "tier": {
        "no": 1,
        "amount": 200000
      },
      "close": 110.2,
      "open": 109.0,
      "high": 111.0,
      "low": 108.1,
      "volume_analysis": {
        "volume_ratio": 1.15,
        "is_volume_burst": false
      },
      "divergence": {
        "status": "NONE",
        "rsi_divergence": false,
        "volume_divergence": false
      },
      "rsi": 52.7,
      "pivots": {
        "daily": 109.77,
        "dailyP": 0.39,
        "weekly": 106.77,
        "weeklyP": 3.21,
        "monthly": 108.57,
        "monthlyP": 1.5,
        "daily_levels": {
          "r1": 111.44,
          "r2": 112.67,
          "r3": 114.34,
          "s1": 108.54,
          "s2": 106.87,
          "s3": 105.64
        },
        "weekly_levels": {
          "r1": 109.63,
          "r2": 112.27,
          "r3": 115.13,
          "s1": 104.13,
          "s2": 101.27,
          "s3": 98.63
        },
        "monthly_levels": {
          "r1": 115.13,
          "r2": 122.87,
          "r3": 129.43,
          "s1": 100.83,
          "s2": 94.27,
          "s3": 86.53
        }
      },
      "ema": {
        "EMA_100": 109.61,
        "EMA_200": 106.97
      },
      "bb": {
        "upper": 114.95,
        "mid": 109.61,
        "lower": 104.26
      }
    },
    {
      "id": 12,
      "ticker": "THYAO",
      "name": "Türk Hava Yolları A.O.",
      "tier": {
        "no": 1,
        "amount": 200000
      },
      "close": 326.0,
      "open": 330.25,
      "high": 330.5,
      "low": 321.5,
      "volume_analysis": {
        "volume_ratio": 0.99,
        "is_volume_burst": false
      },
      "divergence": {
        "status": "NONE",
        "rsi_divergence": false,
        "volume_divergence": false
      },
      "rsi": 49.61,
      "pivots": {
        "daily": 326.0,
        "dailyP": 0.0,
        "weekly": 343.42,
        "weeklyP": -5.07,
        "monthly": 316.75,
        "monthlyP": 2.92,
        "daily_levels": {
          "r1": 330.5,
          "r2": 335.0,
          "r3": 339.5,
          "s1": 321.5,
          "s2": 317.0,
          "s3": 312.5
        },
        "weekly_levels": {
          "r1": 356.58,
          "r2": 368.67,
          "r3": 381.83,
          "s1": 331.33,
          "s2": 318.17,
          "s3": 306.08
        },
        "monthly_levels": {
          "r1": 342.5,
          "r2": 359.0,
          "r3": 384.75,
          "s1": 300.25,
          "s2": 274.5,
          "s3": 258.0
        }
      },
      "ema": {
        "EMA_100": 312.26,
        "EMA_200": 306.19
      },
      "bb": {
        "upper": 346.34,
        "mid": 331.55,
        "lower": 316.76
      }
    },
    {
      "id": 13,
      "ticker": "TUPRS",
      "name": "Türkiye Petrol Rafinerileri A.Ş.",
      "tier": {
        "no": 1,
        "amount": 200000
      },
      "close": 270.75,
      "open": 270.0,
      "high": 273.5,
      "low": 267.75,
      "volume_analysis": {
        "volume_ratio": 0.91,
        "is_volume_burst": false
      },
      "divergence": {
        "status": "VOLUME",
        "rsi_divergence": false,
        "volume_divergence": true
      },
      "rsi": 73.29,
      "pivots": {
        "daily": 270.67,
        "dailyP": 0.03,
        "weekly": 260.0,
        "weeklyP": 4.13,
        "monthly": 231.78,
        "monthlyP": 16.81,
        "daily_levels": {
          "r1": 273.59,
          "r2": 276.42,
          "r3": 279.34,
          "s1": 267.84,
          "s2": 264.92,
          "s3": 262.09
        },
        "weekly_levels": {
          "r1": 277.0,
          "r2": 287.0,
          "r3": 304.0,
          "s1": 250.0,
          "s2": 233.0,
          "s3": 223.0
        },
        "monthly_levels": {
          "r1": 248.47,
          "r2": 269.43,
          "r3": 286.12,
          "s1": 210.82,
          "s2": 194.13,
          "s3": 173.17
        }
      },
      "ema": {
        "EMA_100": 239.45,
        "EMA_200": 223.52
      },
      "bb": {
        "upper": 276.58,
        "mid": 238.86,
        "lower": 201.15
      }
    },
    {
      "id": 18,
      "ticker": "YKBNK",
      "name": "Yapı ve Kredi Bankası A.Ş.",
      "tier": {
        "no": 1,
        "amount": 200000
      },
      "close": 33.96,
      "open": 34.0,
      "high": 34.38,
      "low": 33.78,
      "volume_analysis": {
        "volume_ratio": 1.56,
        "is_volume_burst": false
      },
      "divergence": {
        "status": "NONE",
        "rsi_divergence": false,
        "volume_divergence": false
      },
      "rsi": 31.56,
      "pivots": {
        "daily": 34.04,
        "dailyP": -0.24,
        "weekly": 36.16,
        "weeklyP": -6.08,
        "monthly": 39.1,
        "monthlyP": -13.15,
        "daily_levels": {
          "r1": 34.3,
          "r2": 34.64,
          "r3": 34.9,
          "s1": 33.7,
          "s2": 33.44,
          "s3": 33.1
        },
        "weekly_levels": {
          "r1": 37.38,
          "r2": 39.62,
          "r3": 40.84,
          "s1": 33.92,
          "s2": 32.7,
          "s3": 30.46
        },
        "monthly_levels": {
          "r1": 45.24,
          "r2": 50.34,
          "r3": 56.48,
          "s1": 34.0,
          "s2": 27.86,
          "s3": 22.76
        }
      },
      "ema": {
        "EMA_100": 37.3,
        "EMA_200": 36.11
      },
      "bb": {
        "upper": 45.46,
        "mid": 39.36,
        "lower": 33.27
      }
    }
  ]
}